Workbook

Sheet Final RWA Taxonomy
A1: Component | B1: Governance | E1: Asset | M1: Token Properties | T1: DLT | W1: Economy
A2: Attribute | B2: Governing Law | C2: Legal Entity (Wrapper) | D2: Voting | E2: Custody Arrangement | F2: Ownership Structure | G2: Dispute Forum | H2: Claim & Rights | J2: Asset Type | K2: Verification Mechanisms | M2: Divisibility | N2: Redemption Mechanism | P2: Transferability | Q2: Source of Yield | R2: Yield Distribution Method | S2: Supply | T2: Smart Contract | U2: Chain Deployment | V2: DeFi Integrations | W2: Protocol fees | X2: Access Permissions
A3: Sub-Attribute | B3: Incorporation Jurisdiction | H3: Claim Type | I3: Entitlements | K3: Third-Party Audit | L3: On-Chain Proof | N3: Settlement Form(s) | O3: Burn | X3: Primary Market Access
A4: Definition | B4: Country or territory where the issuing legal entity is formally incorporated/registered | C4: The legal structure of the issuer | D4: Capture whether there is a voting system for tokenholders in the protocol | E4: Arrangement for safekeeping of the underlying | F4: Who holds the legal title to the underlying? | G4: Rule of Law designated for dispute resolution | H4: What does the token represent as a legal or economic claim on the underlying? | I4: What does the token give to the holder as a matter of law? Better rephrased: What actionable rights or entitlements does the token grant to the holder | J4: The category of the real-world asset underlying the token | K4: Independent audit or attestation of the underlying assets by an external firm. This is not related to smart contract audit | L4: On-chain verifiable proof of reserves or asset backing | M4: Can the token be held in sub-units, and to what precision? | N4: What does the holder receive upon redemption? | O4: Is the token burned when redeemed/cancelled? | P4: Constraints on secondary market token movement (wallet-to-wallet transfer, exchange trading). | Q4: What generates returns for the token holder | R4: How yield is delivered to token holders, if applicable | S4: Is the token's supply capped at a predetermined amount? | T4: Which functions of the project are secured, automated, executed through DLT code, and are thus on-chain? | U4: Blockchain(s) on which the token is actively issued and supported by the issuer | V4: How is the token utilized within DeFi protocols? Can it be used as Collateral? | W4: What type of Fees are being charged to the user by the protocol? | X4: Identity and eligibility requirements for acquiring tokens directly from the issuer (minting/purchasing on the PRIMARY market: directly from the issuer)
A5: Possible Values | B5: USA, BVI, Cayman Islands, Switzerland, etc | C5: Direct Issuer: LLC; Gmbh etc | Bankruptcy remote vehicle: SPV; Trust etc | D5: Yes (if so, specify if Quadratic, Single choice, Multiple selection...) | E5: Institutional custodian (regulated); Self-custodied by issuer; Multi-custodian; Decentralized custody; Trust arrangement; Vault storage (physical assets); N/A (for digital-native assets) | F5: Direct title (token holder is legal owner); Beneficial ownership (custodian holds legal title on behalf of user); SPV held; N/A | G5: USA (Federal courts),ICC Arbitration etc | H5: Direct Claim on asset; Pro-rata claim on asset (share of pooled underlying); synthetic exposure (case for derivatives: no direct claim); Debt Instrument (Claim as a creditor) | I5: Redemption right; Income distribution right; Interest entitlement; Governance/voting; Usage/access rights; Net profit participation; No additional rights beyond ownership | J5: Commodity (specify what it is); Real estate; Fixed income (government/corporate bonds); Equities; Art & collectibles; Carbon credits; etc | K5: Yes/No; frequency; provide link | L5: None; Chainlink Proof of Reserve; Smart contract oracle feed; Other | M5: Whole-unit only (minimum 1 token); Fractionalized | N5: Physical delivery (underlying asset); Cash; In-kind (other token); Combination;N/A | O5: Yes/No | P5: Unrestricted; Unrestricted with issuer freeze capability; Whitelist-restricted; Lock-up period (specify duration); Non-transferable; Conditionally restricted (specify) | Q5: None (price appreciation only); Interest income; Rental income; Revenue share; Staking rewards; Lending interest; Dividend; Coupon payments etc | R5: Rebase, Accrual, Distribution, Streaming, Buyback & Burn, Yield Stripping. Definitions: Rebasing=token balance in the wallet is algorithmically adjusted so that accrued yield is expressed as additional token units. If yield = 5% annually, after 1 year 100 tokens will become 105 tokens. Usually each token = 1$ | Accrual= The holder's token count remains permanently fixed from the moment of deposit or purchase. Yield is captured internally by the contract as an increasing exchange rate, share price, or Net Asset Value per token. A holder who deposits 1,000 USDC and receives 1,000 vault shares will, after one year of 5% yield, still hold exactly 1,000 shares, but each share is now redeemable for $1.05 of underlying value. Yield is never explicitly paid out | Distribution= The protocol collects yield from the underlying RWA (interest, rent, invoice settlements, coupons) and transfers it to holders as a separate payment token|Streaming= Yield is transmitted to holders as a continuous, per-second (or per-block) flow rather than in discrete periodic events. | Buyback & Burn = The protocol uses yield generated by the underlying RWA portfolio to purchase its own governance or utility token on the open market (via DEX swaps or OTC), then permanently destroys (burns) the purchased tokens. No yield is delivered directly to any holder in any form | Yield Stripping = A yield-bearing RWA token is decomposed into two independently tradable components: a Principal Token (PT) that entitles the holder to the face value of the underlying at a fixed maturity date, and a Yield Token (YT) that entitles the holder to all yield generated by the underlying between now and that maturity | S5: Capped (if so, specify number), Uncapped | T5: Specify which Component is implemented on-chain; or N/A | U5: Specify Chain | V5: In case it's difficult to classify use YES;NO (Collateral yes/no) Otherwise:None; Collateral in lending (specify protocols); Liquidity pool (specify); Yield vault; Structured product; Staking; Options/perps underlying; Other (specify) | W5: Minting Fee, Redemption Fee, Custody Fee, Yield Spread, Transfer Tax, management fee | X5: Permissionless (anyone can join); KYC gated; Qualified investors only; Institutional only; Whitelisted only

Sheet Classification Work
A1: Component | B1: Preliminary info | F1: Governance | I1: Asset | Q1: Token Properties | X1: DLT | AA1: Economy
A2: Attribute | F2: Governing Law | G2: Legal Entity (Wrapper) | H2: Voting | I2: Custody Arrangement | J2: Ownership Structure | K2: Dispute Forum | L2: Claim & Rights | N2: Asset Type | O2: Verification Mechanisms | Q2: Divisibility | R2: Redemption Mechanism | T2: Transferability | U2: Source of Yield | V2: Yield Distribution Method | W2: Supply | X2: Smart Contract | Y2: Chain Deployment | Z2: DeFi Integrations | AA2: Protocol fees | AB2: Access Permissions
A3: Sub-Attribute | B3: ID | C3: Protocol Name | D3: Date of Classification (DD-MM-YY) | E3: Market Cap Ranking | F3: Incorporation Jurisdiction | L3: Claim Type | M3: Entitlements | O3: Third-Party Audit | P3: On-Chain Proof | R3: Settlement Form(s) | S3: Burn | AB3: Primary Market Access
B4: 1 | C4: Tether Gold (XAUt) | D4: 46112 | E4: 1 | F4: {=_xlfn.LET( _xlpm.project,TRIM($C4), _xlpm.attribute,TRIM(IF(F$3<>"",F$3,F$2)), _xlfn.XLOOKUP( 1, (TRIM(Sources!$B$2:$B$461)=_xlpm.project)*(TRIM(Sources!$D$2:$D$461)=_xlpm.attribute), Sources!$E$2:$E$461, "UNKNOWN" ) )} -> El Salvador | G4: {=_xlfn.LET( _xlpm.project,TRIM($C4), _xlpm.attribute,TRIM(IF(G$3<>"",G$3,G$2)), _xlfn.XLOOKUP( 1, (TRIM(Sources!$B$2:$B$461)=_xlpm.project)*(TRIM(Sources!$D$2:$D$461)=_xlpm.attribute), Sources!$E$2:$E$461, "UNKNOWN" ) )} -> Direct Issuer: SA de C.V. | H4: {=_xlfn.LET( _xlpm.project,TRIM($C4), _xlpm.attribute,TRIM(IF(H$3<>"",H$3,H$2)), _xlfn.XLOOKUP( 1, (TRIM(Sources!$B$2:$B$461)=_xlpm.project)*(TRIM(Sources!$D$2:$D$461)=_xlpm.attribute), Sources!$E$2:$E$461, "UNKNOWN" ) )} -> N/A | I4: {=_xlfn.LET( _xlpm.project,TRIM($C4), _xlpm.attribute,TRIM(IF(I$3<>"",I$3,I$2)), _xlfn.XLOOKUP( 1, (TRIM(Sources!$B$2:$B$461)=_xlpm.project)*(TRIM(Sources!$D$2:$D$461)=_xlpm.attribute), Sources!$E$2:$E$461, "UNKNOWN" ) )} -> Vault storage (physical assets) | J4: {=_xlfn.LET( _xlpm.project,TRIM($C4), _xlpm.attribute,TRIM(IF(J$3<>"",J$3,J$2)), _xlfn.XLOOKUP( 1, (TRIM(Sources!$B$2:$B$461)=_xlpm.project)*(TRIM(Sources!$D$2:$D$461)=_xlpm.attribute), Sources!$E$2:$E$461, "UNKNOWN" ) )} -> Beneficial ownership (custodian holds legal title on behalf of user) | K4: {=_xlfn.LET( _xlpm.project,TRIM($C4), _xlpm.attribute,TRIM(IF(K$3<>"",K$3,K$2)), _xlfn.XLOOKUP( 1, (TRIM(Sources!$B$2:$B$461)=_xlpm.project)*(TRIM(Sources!$D$2:$D$461)=_xlpm.attribute), Sources!$E$2:$E$461, "UNKNOWN" ) )} -> CPR Arbitration; BVI law | L4: {=_xlfn.LET( _xlpm.project,TRIM($C4), _xlpm.attribute,TRIM(IF(L$3<>"",L$3,L$2)), _xlfn.XLOOKUP( 1, (TRIM(Sources!$B$2:$B$461)=_xlpm.project)*(TRIM(Sources!$D$2:$D$461)=_xlpm.attribute), Sources!$E$2:$E$461, "UNKNOWN" ) )} -> Direct Claim on asset | M4: {=_xlfn.LET( _xlpm.project,TRIM($C4), _xlpm.attribute,TRIM(IF(M$3<>"",M$3,M$2)), _xlfn.XLOOKUP( 1, (TRIM(Sources!$B$2:$B$461)=_xlpm.project)*(TRIM(Sources!$D$2:$D$461)=_xlpm.attribute), Sources!$E$2:$E$461, "UNKNOWN" ) )} -> Redemption right | ... AB4: {=_xlfn.LET( _xlpm.project,TRIM($C4), _xlpm.attribute,TRIM(IF(AB$3<>"",AB$3,AB$2)), _xlfn.XLOOKUP( 1, (TRIM(Sources!$B$2:$B$461)=_xlpm.project)*(TRIM(Sources!$D$2:$D$461)=_xlpm.attribute), Sources!$E$2:$E$461, "UNKNOWN" ) )} -> KYC gated
B5: 2 | C5: BUIDL | D5: 46112 | E5: 2 | F5: {=_xlfn.LET( _xlpm.project,TRIM($C5), _xlpm.attribute,TRIM(IF(F$3<>"",F$3,F$2)), _xlfn.XLOOKUP( 1, (TRIM(Sources!$B$2:$B$461)=_xlpm.project)*(TRIM(Sources!$D$2:$D$461)=_xlpm.attribute), Sources!$E$2:$E$461, "UNKNOWN" ) )} -> BVI | G5: {=_xlfn.LET( _xlpm.project,TRIM($C5), _xlpm.attribute,TRIM(IF(G$3<>"",G$3,G$2)), _xlfn.XLOOKUP( 1, (TRIM(Sources!$B$2:$B$461)=_xlpm.project)*(TRIM(Sources!$D$2:$D$461)=_xlpm.attribute), Sources!$E$2:$E$461, "UNKNOWN" ) )} -> Direct Issuer: Ltd. | H5: {=_xlfn.LET( _xlpm.project,TRIM($C5), _xlpm.attribute,TRIM(IF(H$3<>"",H$3,H$2)), _xlfn.XLOOKUP( 1, (TRIM(Sources!$B$2:$B$461)=_xlpm.project)*(TRIM(Sources!$D$2:$D$461)=_xlpm.attribute), Sources!$E$2:$E$461, "UNKNOWN" ) )} -> No token-holder voting system identified for the tokenized fund; BUIDL is not DAO-governed. | I5: {=_xlfn.LET( _xlpm.project,TRIM($C5), _xlpm.attribute,TRIM(IF(I$3<>"",I$3,I$2)), _xlfn.XLOOKUP( 1, (TRIM(Sources!$B$2:$B$461)=_xlpm.project)*(TRIM(Sources!$D$2:$D$461)=_xlpm.attribute), Sources!$E$2:$E$461, "UNKNOWN" ) )} -> Institutional custodian (regulated) | J5: {=_xlfn.LET( _xlpm.project,TRIM($C5), _xlpm.attribute,TRIM(IF(J$3<>"",J$3,J$2)), _xlfn.XLOOKUP( 1, (TRIM(Sources!$B$2:$B$461)=_xlpm.project)*(TRIM(Sources!$D$2:$D$461)=_xlpm.attribute), Sources!$E$2:$E$461, "UNKNOWN" ) )} -> Beneficial ownership (custodian holds legal title on behalf of user) | K5: {=_xlfn.LET( _xlpm.project,TRIM($C5), _xlpm.attribute,TRIM(IF(K$3<>"",K$3,K$2)), _xlfn.XLOOKUP( 1, (TRIM(Sources!$B$2:$B$461)=_xlpm.project)*(TRIM(Sources!$D$2:$D$461)=_xlpm.attribute), Sources!$E$2:$E$461, "UNKNOWN" ) )} -> Delaware, Disputes resolved in New York | L5: {=_xlfn.LET( _xlpm.project,TRIM($C5), _xlpm.attribute,TRIM(IF(L$3<>"",L$3,L$2)), _xlfn.XLOOKUP( 1, (TRIM(Sources!$B$2:$B$461)=_xlpm.project)*(TRIM(Sources!$D$2:$D$461)=_xlpm.attribute), Sources!$E$2:$E$461, "UNKNOWN" ) )} -> Pro-rata claim on asset (share of pooled underlying) | M5: {=_xlfn.LET( _xlpm.project,TRIM($C5), _xlpm.attribute,TRIM(IF(M$3<>"",M$3,M$2)), _xlfn.XLOOKUP( 1, (TRIM(Sources!$B$2:$B$461)=_xlpm.project)*(TRIM(Sources!$D$2:$D$461)=_xlpm.attribute), Sources!$E$2:$E$461, "UNKNOWN" ) )} -> Redemption right; Income distribution right | ... AB5: {=_xlfn.LET( _xlpm.project,TRIM($C5), _xlpm.attribute,TRIM(IF(AB$3<>"",AB$3,AB$2)), _xlfn.XLOOKUP( 1, (TRIM(Sources!$B$2:$B$461)=_xlpm.project)*(TRIM(Sources!$D$2:$D$461)=_xlpm.attribute), Sources!$E$2:$E$461, "UNKNOWN" ) )} -> Qualified investors only
B6: 3 | C6: PAX Gold | D6: 46113 | E6: 3 | F6: {=_xlfn.LET( _xlpm.project,TRIM($C6), _xlpm.attribute,TRIM(IF(F$3<>"",F$3,F$2)), _xlfn.XLOOKUP( 1, (TRIM(Sources!$B$2:$B$461)=_xlpm.project)*(TRIM(Sources!$D$2:$D$461)=_xlpm.attribute), Sources!$E$2:$E$461, "UNKNOWN" ) )} -> USA | G6: {=_xlfn.LET( _xlpm.project,TRIM($C6), _xlpm.attribute,TRIM(IF(G$3<>"",G$3,G$2)), _xlfn.XLOOKUP( 1, (TRIM(Sources!$B$2:$B$461)=_xlpm.project)*(TRIM(Sources!$D$2:$D$461)=_xlpm.attribute), Sources!$E$2:$E$461, "UNKNOWN" ) )} -> Direct Issuer: N.A. | H6: {=_xlfn.LET( _xlpm.project,TRIM($C6), _xlpm.attribute,TRIM(IF(H$3<>"",H$3,H$2)), _xlfn.XLOOKUP( 1, (TRIM(Sources!$B$2:$B$461)=_xlpm.project)*(TRIM(Sources!$D$2:$D$461)=_xlpm.attribute), Sources!$E$2:$E$461, "UNKNOWN" ) )} -> No voting system identified. | I6: {=_xlfn.LET( _xlpm.project,TRIM($C6), _xlpm.attribute,TRIM(IF(I$3<>"",I$3,I$2)), _xlfn.XLOOKUP( 1, (TRIM(Sources!$B$2:$B$461)=_xlpm.project)*(TRIM(Sources!$D$2:$D$461)=_xlpm.attribute), Sources!$E$2:$E$461, "UNKNOWN" ) )} -> Vault storage (physical assets) | J6: {=_xlfn.LET( _xlpm.project,TRIM($C6), _xlpm.attribute,TRIM(IF(J$3<>"",J$3,J$2)), _xlfn.XLOOKUP( 1, (TRIM(Sources!$B$2:$B$461)=_xlpm.project)*(TRIM(Sources!$D$2:$D$461)=_xlpm.attribute), Sources!$E$2:$E$461, "UNKNOWN" ) )} -> Beneficial ownership (custodian holds legal title on behalf of user) | K6: {=_xlfn.LET( _xlpm.project,TRIM($C6), _xlpm.attribute,TRIM(IF(K$3<>"",K$3,K$2)), _xlfn.XLOOKUP( 1, (TRIM(Sources!$B$2:$B$461)=_xlpm.project)*(TRIM(Sources!$D$2:$D$461)=_xlpm.attribute), Sources!$E$2:$E$461, "UNKNOWN" ) )} -> Binding arbitration; New York law | L6: {=_xlfn.LET( _xlpm.project,TRIM($C6), _xlpm.attribute,TRIM(IF(L$3<>"",L$3,L$2)), _xlfn.XLOOKUP( 1, (TRIM(Sources!$B$2:$B$461)=_xlpm.project)*(TRIM(Sources!$D$2:$D$461)=_xlpm.attribute), Sources!$E$2:$E$461, "UNKNOWN" ) )} -> Pro-rata claim on asset (share of pooled underlying) | M6: {=_xlfn.LET( _xlpm.project,TRIM($C6), _xlpm.attribute,TRIM(IF(M$3<>"",M$3,M$2)), _xlfn.XLOOKUP( 1, (TRIM(Sources!$B$2:$B$461)=_xlpm.project)*(TRIM(Sources!$D$2:$D$461)=_xlpm.attribute), Sources!$E$2:$E$461, "UNKNOWN" ) )} -> Redemption right | ... AB6: {=_xlfn.LET( _xlpm.project,TRIM($C6), _xlpm.attribute,TRIM(IF(AB$3<>"",AB$3,AB$2)), _xlfn.XLOOKUP( 1, (TRIM(Sources!$B$2:$B$461)=_xlpm.project)*(TRIM(Sources!$D$2:$D$461)=_xlpm.attribute), Sources!$E$2:$E$461, "UNKNOWN" ) )} -> KYC gated
B7: 4 | C7: US Yield Coin (UYSC) | D7: 46139 | E7: 4 | F7: {=_xlfn.LET( _xlpm.project,TRIM($C7), _xlpm.attribute,TRIM(IF(F$3<>"",F$3,F$2)), _xlfn.XLOOKUP( 1, (TRIM(Sources!$B$2:$B$461)=_xlpm.project)*(TRIM(Sources!$D$2:$D$461)=_xlpm.attribute), Sources!$E$2:$E$461, "UNKNOWN" ) )} -> Bermuda | G7: {=_xlfn.LET( _xlpm.project,TRIM($C7), _xlpm.attribute,TRIM(IF(G$3<>"",G$3,G$2)), _xlfn.XLOOKUP( 1, (TRIM(Sources!$B$2:$B$461)=_xlpm.project)*(TRIM(Sources!$D$2:$D$461)=_xlpm.attribute), Sources!$E$2:$E$461, "UNKNOWN" ) )} -> Direct Issuer: Ltd. | H7: {=_xlfn.LET( _xlpm.project,TRIM($C7), _xlpm.attribute,TRIM(IF(H$3<>"",H$3,H$2)), _xlfn.XLOOKUP( 1, (TRIM(Sources!$B$2:$B$461)=_xlpm.project)*(TRIM(Sources!$D$2:$D$461)=_xlpm.attribute), Sources!$E$2:$E$461, "UNKNOWN" ) )} -> UNKNOWN | I7: {=_xlfn.LET( _xlpm.project,TRIM($C7), _xlpm.attribute,TRIM(IF(I$3<>"",I$3,I$2)), _xlfn.XLOOKUP( 1, (TRIM(Sources!$B$2:$B$461)=_xlpm.project)*(TRIM(Sources!$D$2:$D$461)=_xlpm.attribute), Sources!$E$2:$E$461, "UNKNOWN" ) )} -> Institutional custodian (regulated) | J7: {=_xlfn.LET( _xlpm.project,TRIM($C7), _xlpm.attribute,TRIM(IF(J$3<>"",J$3,J$2)), _xlfn.XLOOKUP( 1, (TRIM(Sources!$B$2:$B$461)=_xlpm.project)*(TRIM(Sources!$D$2:$D$461)=_xlpm.attribute), Sources!$E$2:$E$461, "UNKNOWN" ) )} -> Beneficial ownership (custodian holds legal title on behalf of user) | K7: {=_xlfn.LET( _xlpm.project,TRIM($C7), _xlpm.attribute,TRIM(IF(K$3<>"",K$3,K$2)), _xlfn.XLOOKUP( 1, (TRIM(Sources!$B$2:$B$461)=_xlpm.project)*(TRIM(Sources!$D$2:$D$461)=_xlpm.attribute), Sources!$E$2:$E$461, "UNKNOWN" ) )} -> UNKNOWN | L7: {=_xlfn.LET( _xlpm.project,TRIM($C7), _xlpm.attribute,TRIM(IF(L$3<>"",L$3,L$2)), _xlfn.XLOOKUP( 1, (TRIM(Sources!$B$2:$B$461)=_xlpm.project)*(TRIM(Sources!$D$2:$D$461)=_xlpm.attribute), Sources!$E$2:$E$461, "UNKNOWN" ) )} -> Pro-rata claim on asset (share of pooled underlying) | M7: {=_xlfn.LET( _xlpm.project,TRIM($C7), _xlpm.attribute,TRIM(IF(M$3<>"",M$3,M$2)), _xlfn.XLOOKUP( 1, (TRIM(Sources!$B$2:$B$461)=_xlpm.project)*(TRIM(Sources!$D$2:$D$461)=_xlpm.attribute), Sources!$E$2:$E$461, "UNKNOWN" ) )} -> Redemption right; Interest entitlement | ... AB7: {=_xlfn.LET( _xlpm.project,TRIM($C7), _xlpm.attribute,TRIM(IF(AB$3<>"",AB$3,AB$2)), _xlfn.XLOOKUP( 1, (TRIM(Sources!$B$2:$B$461)=_xlpm.project)*(TRIM(Sources!$D$2:$D$461)=_xlpm.attribute), Sources!$E$2:$E$461, "UNKNOWN" ) )} -> Institutional only; KYC gated; Whitelisted only
B8: 5 | C8: Superstate USTB | D8: 46139 | E8: 5 | F8: {=_xlfn.LET( _xlpm.project,TRIM($C8), _xlpm.attribute,TRIM(IF(F$3<>"",F$3,F$2)), _xlfn.XLOOKUP( 1, (TRIM(Sources!$B$2:$B$461)=_xlpm.project)*(TRIM(Sources!$D$2:$D$461)=_xlpm.attribute), Sources!$E$2:$E$461, "UNKNOWN" ) )} -> USA | G8: {=_xlfn.LET( _xlpm.project,TRIM($C8), _xlpm.attribute,TRIM(IF(G$3<>"",G$3,G$2)), _xlfn.XLOOKUP( 1, (TRIM(Sources!$B$2:$B$461)=_xlpm.project)*(TRIM(Sources!$D$2:$D$461)=_xlpm.attribute), Sources!$E$2:$E$461, "UNKNOWN" ) )} -> Bankruptcy remote vehicle: Trust | H8: {=_xlfn.LET( _xlpm.project,TRIM($C8), _xlpm.attribute,TRIM(IF(H$3<>"",H$3,H$2)), _xlfn.XLOOKUP( 1, (TRIM(Sources!$B$2:$B$461)=_xlpm.project)*(TRIM(Sources!$D$2:$D$461)=_xlpm.attribute), Sources!$E$2:$E$461, "UNKNOWN" ) )} -> UNKNOWN | I8: {=_xlfn.LET( _xlpm.project,TRIM($C8), _xlpm.attribute,TRIM(IF(I$3<>"",I$3,I$2)), _xlfn.XLOOKUP( 1, (TRIM(Sources!$B$2:$B$461)=_xlpm.project)*(TRIM(Sources!$D$2:$D$461)=_xlpm.attribute), Sources!$E$2:$E$461, "UNKNOWN" ) )} -> Institutional custodian (regulated) | J8: {=_xlfn.LET( _xlpm.project,TRIM($C8), _xlpm.attribute,TRIM(IF(J$3<>"",J$3,J$2)), _xlfn.XLOOKUP( 1, (TRIM(Sources!$B$2:$B$461)=_xlpm.project)*(TRIM(Sources!$D$2:$D$461)=_xlpm.attribute), Sources!$E$2:$E$461, "UNKNOWN" ) )} -> SPV held | K8: {=_xlfn.LET( _xlpm.project,TRIM($C8), _xlpm.attribute,TRIM(IF(K$3<>"",K$3,K$2)), _xlfn.XLOOKUP( 1, (TRIM(Sources!$B$2:$B$461)=_xlpm.project)*(TRIM(Sources!$D$2:$D$461)=_xlpm.attribute), Sources!$E$2:$E$461, "UNKNOWN" ) )} -> UNKNOWN | L8: {=_xlfn.LET( _xlpm.project,TRIM($C8), _xlpm.attribute,TRIM(IF(L$3<>"",L$3,L$2)), _xlfn.XLOOKUP( 1, (TRIM(Sources!$B$2:$B$461)=_xlpm.project)*(TRIM(Sources!$D$2:$D$461)=_xlpm.attribute), Sources!$E$2:$E$461, "UNKNOWN" ) )} -> Pro-rata claim on asset (share of pooled underlying) | M8: {=_xlfn.LET( _xlpm.project,TRIM($C8), _xlpm.attribute,TRIM(IF(M$3<>"",M$3,M$2)), _xlfn.XLOOKUP( 1, (TRIM(Sources!$B$2:$B$461)=_xlpm.project)*(TRIM(Sources!$D$2:$D$461)=_xlpm.attribute), Sources!$E$2:$E$461, "UNKNOWN" ) )} -> Redemption right; Interest entitlement | ... AB8: {=_xlfn.LET( _xlpm.project,TRIM($C8), _xlpm.attribute,TRIM(IF(AB$3<>"",AB$3,AB$2)), _xlfn.XLOOKUP( 1, (TRIM(Sources!$B$2:$B$461)=_xlpm.project)*(TRIM(Sources!$D$2:$D$461)=_xlpm.attribute), Sources!$E$2:$E$461, "UNKNOWN" ) )} -> Qualified investors only; KYC gated; Whitelisted only
B9: 6 | C9: WisdomTree Treasury Money Market Digital Fund (WTGXX) | D9: 46139 | E9: 6 | F9: {=_xlfn.LET( _xlpm.project,TRIM($C9), _xlpm.attribute,TRIM(IF(F$3<>"",F$3,F$2)), _xlfn.XLOOKUP( 1, (TRIM(Sources!$B$2:$B$461)=_xlpm.project)*(TRIM(Sources!$D$2:$D$461)=_xlpm.attribute), Sources!$E$2:$E$461, "UNKNOWN" ) )} -> USA | G9: {=_xlfn.LET( _xlpm.project,TRIM($C9), _xlpm.attribute,TRIM(IF(G$3<>"",G$3,G$2)), _xlfn.XLOOKUP( 1, (TRIM(Sources!$B$2:$B$461)=_xlpm.project)*(TRIM(Sources!$D$2:$D$461)=_xlpm.attribute), Sources!$E$2:$E$461, "UNKNOWN" ) )} -> Bankruptcy remote vehicle: Trust | H9: {=_xlfn.LET( _xlpm.project,TRIM($C9), _xlpm.attribute,TRIM(IF(H$3<>"",H$3,H$2)), _xlfn.XLOOKUP( 1, (TRIM(Sources!$B$2:$B$461)=_xlpm.project)*(TRIM(Sources!$D$2:$D$461)=_xlpm.attribute), Sources!$E$2:$E$461, "UNKNOWN" ) )} -> Yes (shareholder voting; one vote per share when required) | I9: {=_xlfn.LET( _xlpm.project,TRIM($C9), _xlpm.attribute,TRIM(IF(I$3<>"",I$3,I$2)), _xlfn.XLOOKUP( 1, (TRIM(Sources!$B$2:$B$461)=_xlpm.project)*(TRIM(Sources!$D$2:$D$461)=_xlpm.attribute), Sources!$E$2:$E$461, "UNKNOWN" ) )} -> Institutional custodian (regulated) | J9: {=_xlfn.LET( _xlpm.project,TRIM($C9), _xlpm.attribute,TRIM(IF(J$3<>"",J$3,J$2)), _xlfn.XLOOKUP( 1, (TRIM(Sources!$B$2:$B$461)=_xlpm.project)*(TRIM(Sources!$D$2:$D$461)=_xlpm.attribute), Sources!$E$2:$E$461, "UNKNOWN" ) )} -> SPV held | K9: {=_xlfn.LET( _xlpm.project,TRIM($C9), _xlpm.attribute,TRIM(IF(K$3<>"",K$3,K$2)), _xlfn.XLOOKUP( 1, (TRIM(Sources!$B$2:$B$461)=_xlpm.project)*(TRIM(Sources!$D$2:$D$461)=_xlpm.attribute), Sources!$E$2:$E$461, "UNKNOWN" ) )} -> AAA Arbitration; New York, New York | L9: {=_xlfn.LET( _xlpm.project,TRIM($C9), _xlpm.attribute,TRIM(IF(L$3<>"",L$3,L$2)), _xlfn.XLOOKUP( 1, (TRIM(Sources!$B$2:$B$461)=_xlpm.project)*(TRIM(Sources!$D$2:$D$461)=_xlpm.attribute), Sources!$E$2:$E$461, "UNKNOWN" ) )} -> Pro-rata claim on asset (share of pooled underlying) | M9: {=_xlfn.LET( _xlpm.project,TRIM($C9), _xlpm.attribute,TRIM(IF(M$3<>"",M$3,M$2)), _xlfn.XLOOKUP( 1, (TRIM(Sources!$B$2:$B$461)=_xlpm.project)*(TRIM(Sources!$D$2:$D$461)=_xlpm.attribute), Sources!$E$2:$E$461, "UNKNOWN" ) )} -> Redemption right; Income distribution right; Governance/voting | ... AB9: {=_xlfn.LET( _xlpm.project,TRIM($C9), _xlpm.attribute,TRIM(IF(AB$3<>"",AB$3,AB$2)), _xlfn.XLOOKUP( 1, (TRIM(Sources!$B$2:$B$461)=_xlpm.project)*(TRIM(Sources!$D$2:$D$461)=_xlpm.attribute), Sources!$E$2:$E$461, "UNKNOWN" ) )} -> KYC gated; Whitelisted only
B10: 7 | C10: Janus Henderson Anemoy AAA CLO Fund (JAAA) | D10: 46139 | E10: 7 | F10: {=_xlfn.LET( _xlpm.project,TRIM($C10), _xlpm.attribute,TRIM(IF(F$3<>"",F$3,F$2)), _xlfn.XLOOKUP( 1, (TRIM(Sources!$B$2:$B$461)=_xlpm.project)*(TRIM(Sources!$D$2:$D$461)=_xlpm.attribute), Sources!$E$2:$E$461, "UNKNOWN" ) )} -> BVI | G10: {=_xlfn.LET( _xlpm.project,TRIM($C10), _xlpm.attribute,TRIM(IF(G$3<>"",G$3,G$2)), _xlfn.XLOOKUP( 1, (TRIM(Sources!$B$2:$B$461)=_xlpm.project)*(TRIM(Sources!$D$2:$D$461)=_xlpm.attribute), Sources!$E$2:$E$461, "UNKNOWN" ) )} -> Bankruptcy remote vehicle: SPV | H10: {=_xlfn.LET( _xlpm.project,TRIM($C10), _xlpm.attribute,TRIM(IF(H$3<>"",H$3,H$2)), _xlfn.XLOOKUP( 1, (TRIM(Sources!$B$2:$B$461)=_xlpm.project)*(TRIM(Sources!$D$2:$D$461)=_xlpm.attribute), Sources!$E$2:$E$461, "UNKNOWN" ) )} -> UNKNOWN | I10: {=_xlfn.LET( _xlpm.project,TRIM($C10), _xlpm.attribute,TRIM(IF(I$3<>"",I$3,I$2)), _xlfn.XLOOKUP( 1, (TRIM(Sources!$B$2:$B$461)=_xlpm.project)*(TRIM(Sources!$D$2:$D$461)=_xlpm.attribute), Sources!$E$2:$E$461, "UNKNOWN" ) )} -> Institutional custodian (regulated) | J10: {=_xlfn.LET( _xlpm.project,TRIM($C10), _xlpm.attribute,TRIM(IF(J$3<>"",J$3,J$2)), _xlfn.XLOOKUP( 1, (TRIM(Sources!$B$2:$B$461)=_xlpm.project)*(TRIM(Sources!$D$2:$D$461)=_xlpm.attribute), Sources!$E$2:$E$461, "UNKNOWN" ) )} -> SPV held | K10: {=_xlfn.LET( _xlpm.project,TRIM($C10), _xlpm.attribute,TRIM(IF(K$3<>"",K$3,K$2)), _xlfn.XLOOKUP( 1, (TRIM(Sources!$B$2:$B$461)=_xlpm.project)*(TRIM(Sources!$D$2:$D$461)=_xlpm.attribute), Sources!$E$2:$E$461, "UNKNOWN" ) )} -> UNKNOWN | L10: {=_xlfn.LET( _xlpm.project,TRIM($C10), _xlpm.attribute,TRIM(IF(L$3<>"",L$3,L$2)), _xlfn.XLOOKUP( 1, (TRIM(Sources!$B$2:$B$461)=_xlpm.project)*(TRIM(Sources!$D$2:$D$461)=_xlpm.attribute), Sources!$E$2:$E$461, "UNKNOWN" ) )} -> Pro-rata claim on asset (share of pooled underlying) | M10: {=_xlfn.LET( _xlpm.project,TRIM($C10), _xlpm.attribute,TRIM(IF(M$3<>"",M$3,M$2)), _xlfn.XLOOKUP( 1, (TRIM(Sources!$B$2:$B$461)=_xlpm.project)*(TRIM(Sources!$D$2:$D$461)=_xlpm.attribute), Sources!$E$2:$E$461, "UNKNOWN" ) )} -> Redemption right; Interest entitlement | ... AB10: {=_xlfn.LET( _xlpm.project,TRIM($C10), _xlpm.attribute,TRIM(IF(AB$3<>"",AB$3,AB$2)), _xlfn.XLOOKUP( 1, (TRIM(Sources!$B$2:$B$461)=_xlpm.project)*(TRIM(Sources!$D$2:$D$461)=_xlpm.attribute), Sources!$E$2:$E$461, "UNKNOWN" ) )} -> Qualified investors only
B11: 8 | C11: Janus Henderson Anemoy Treasury Fund (JTRSY) | D11: 46139 | E11: 8 | F11: {=_xlfn.LET( _xlpm.project,TRIM($C11), _xlpm.attribute,TRIM(IF(F$3<>"",F$3,F$2)), _xlfn.XLOOKUP( 1, (TRIM(Sources!$B$2:$B$461)=_xlpm.project)*(TRIM(Sources!$D$2:$D$461)=_xlpm.attribute), Sources!$E$2:$E$461, "UNKNOWN" ) )} -> BVI | G11: {=_xlfn.LET( _xlpm.project,TRIM($C11), _xlpm.attribute,TRIM(IF(G$3<>"",G$3,G$2)), _xlfn.XLOOKUP( 1, (TRIM(Sources!$B$2:$B$461)=_xlpm.project)*(TRIM(Sources!$D$2:$D$461)=_xlpm.attribute), Sources!$E$2:$E$461, "UNKNOWN" ) )} -> Bankruptcy remote vehicle: SPV | H11: {=_xlfn.LET( _xlpm.project,TRIM($C11), _xlpm.attribute,TRIM(IF(H$3<>"",H$3,H$2)), _xlfn.XLOOKUP( 1, (TRIM(Sources!$B$2:$B$461)=_xlpm.project)*(TRIM(Sources!$D$2:$D$461)=_xlpm.attribute), Sources!$E$2:$E$461, "UNKNOWN" ) )} -> UNKNOWN | I11: {=_xlfn.LET( _xlpm.project,TRIM($C11), _xlpm.attribute,TRIM(IF(I$3<>"",I$3,I$2)), _xlfn.XLOOKUP( 1, (TRIM(Sources!$B$2:$B$461)=_xlpm.project)*(TRIM(Sources!$D$2:$D$461)=_xlpm.attribute), Sources!$E$2:$E$461, "UNKNOWN" ) )} -> Institutional custodian (regulated) | J11: {=_xlfn.LET( _xlpm.project,TRIM($C11), _xlpm.attribute,TRIM(IF(J$3<>"",J$3,J$2)), _xlfn.XLOOKUP( 1, (TRIM(Sources!$B$2:$B$461)=_xlpm.project)*(TRIM(Sources!$D$2:$D$461)=_xlpm.attribute), Sources!$E$2:$E$461, "UNKNOWN" ) )} -> Direct title (token holder is legal owner) | K11: {=_xlfn.LET( _xlpm.project,TRIM($C11), _xlpm.attribute,TRIM(IF(K$3<>"",K$3,K$2)), _xlfn.XLOOKUP( 1, (TRIM(Sources!$B$2:$B$461)=_xlpm.project)*(TRIM(Sources!$D$2:$D$461)=_xlpm.attribute), Sources!$E$2:$E$461, "UNKNOWN" ) )} -> UNKNOWN | L11: {=_xlfn.LET( _xlpm.project,TRIM($C11), _xlpm.attribute,TRIM(IF(L$3<>"",L$3,L$2)), _xlfn.XLOOKUP( 1, (TRIM(Sources!$B$2:$B$461)=_xlpm.project)*(TRIM(Sources!$D$2:$D$461)=_xlpm.attribute), Sources!$E$2:$E$461, "UNKNOWN" ) )} -> Pro-rata claim on asset (share of pooled underlying) | M11: {=_xlfn.LET( _xlpm.project,TRIM($C11), _xlpm.attribute,TRIM(IF(M$3<>"",M$3,M$2)), _xlfn.XLOOKUP( 1, (TRIM(Sources!$B$2:$B$461)=_xlpm.project)*(TRIM(Sources!$D$2:$D$461)=_xlpm.attribute), Sources!$E$2:$E$461, "UNKNOWN" ) )} -> Redemption right; Interest entitlement | ... AB11: {=_xlfn.LET( _xlpm.project,TRIM($C11), _xlpm.attribute,TRIM(IF(AB$3<>"",AB$3,AB$2)), _xlfn.XLOOKUP( 1, (TRIM(Sources!$B$2:$B$461)=_xlpm.project)*(TRIM(Sources!$D$2:$D$461)=_xlpm.attribute), Sources!$E$2:$E$461, "UNKNOWN" ) )} -> Qualified investors only; Whitelisted only
B12: 9 | C12: Ondo OUSG | D12: 46143 | E12: 9 | F12: {=_xlfn.LET( _xlpm.project,TRIM($C12), _xlpm.attribute,TRIM(IF(F$3<>"",F$3,F$2)), _xlfn.XLOOKUP( 1, (TRIM(Sources!$B$2:$B$461)=_xlpm.project)*(TRIM(Sources!$D$2:$D$461)=_xlpm.attribute), Sources!$E$2:$E$461, "UNKNOWN" ) )} -> USA | G12: {=_xlfn.LET( _xlpm.project,TRIM($C12), _xlpm.attribute,TRIM(IF(G$3<>"",G$3,G$2)), _xlfn.XLOOKUP( 1, (TRIM(Sources!$B$2:$B$461)=_xlpm.project)*(TRIM(Sources!$D$2:$D$461)=_xlpm.attribute), Sources!$E$2:$E$461, "UNKNOWN" ) )} -> Direct Issuer: LP | H12: {=_xlfn.LET( _xlpm.project,TRIM($C12), _xlpm.attribute,TRIM(IF(H$3<>"",H$3,H$2)), _xlfn.XLOOKUP( 1, (TRIM(Sources!$B$2:$B$461)=_xlpm.project)*(TRIM(Sources!$D$2:$D$461)=_xlpm.attribute), Sources!$E$2:$E$461, "UNKNOWN" ) )} -> UNKNOWN | I12: {=_xlfn.LET( _xlpm.project,TRIM($C12), _xlpm.attribute,TRIM(IF(I$3<>"",I$3,I$2)), _xlfn.XLOOKUP( 1, (TRIM(Sources!$B$2:$B$461)=_xlpm.project)*(TRIM(Sources!$D$2:$D$461)=_xlpm.attribute), Sources!$E$2:$E$461, "UNKNOWN" ) )} -> Institutional custodian (regulated) | J12: {=_xlfn.LET( _xlpm.project,TRIM($C12), _xlpm.attribute,TRIM(IF(J$3<>"",J$3,J$2)), _xlfn.XLOOKUP( 1, (TRIM(Sources!$B$2:$B$461)=_xlpm.project)*(TRIM(Sources!$D$2:$D$461)=_xlpm.attribute), Sources!$E$2:$E$461, "UNKNOWN" ) )} -> OTHER - Limited Partnership | K12: {=_xlfn.LET( _xlpm.project,TRIM($C12), _xlpm.attribute,TRIM(IF(K$3<>"",K$3,K$2)), _xlfn.XLOOKUP( 1, (TRIM(Sources!$B$2:$B$461)=_xlpm.project)*(TRIM(Sources!$D$2:$D$461)=_xlpm.attribute), Sources!$E$2:$E$461, "UNKNOWN" ) )} -> UNKNOWN | L12: {=_xlfn.LET( _xlpm.project,TRIM($C12), _xlpm.attribute,TRIM(IF(L$3<>"",L$3,L$2)), _xlfn.XLOOKUP( 1, (TRIM(Sources!$B$2:$B$461)=_xlpm.project)*(TRIM(Sources!$D$2:$D$461)=_xlpm.attribute), Sources!$E$2:$E$461, "UNKNOWN" ) )} -> Pro-rata claim on asset (share of pooled underlying) | M12: {=_xlfn.LET( _xlpm.project,TRIM($C12), _xlpm.attribute,TRIM(IF(M$3<>"",M$3,M$2)), _xlfn.XLOOKUP( 1, (TRIM(Sources!$B$2:$B$461)=_xlpm.project)*(TRIM(Sources!$D$2:$D$461)=_xlpm.attribute), Sources!$E$2:$E$461, "UNKNOWN" ) )} -> Redemption right; Interest entitlement | ... AB12: {=_xlfn.LET( _xlpm.project,TRIM($C12), _xlpm.attribute,TRIM(IF(AB$3<>"",AB$3,AB$2)), _xlfn.XLOOKUP( 1, (TRIM(Sources!$B$2:$B$461)=_xlpm.project)*(TRIM(Sources!$D$2:$D$461)=_xlpm.attribute), Sources!$E$2:$E$461, "UNKNOWN" ) )} -> Qualified investors only; KYC gated; Whitelisted only
B13: 10 | C13: BlackRock USD Institutional Digital Liquidity Fund - I Class (BUIDL-I) | D13: 46143 | E13: 10 | F13: {=_xlfn.LET( _xlpm.project,TRIM($C13), _xlpm.attribute,TRIM(IF(F$3<>"",F$3,F$2)), _xlfn.XLOOKUP( 1, (TRIM(Sources!$B$2:$B$461)=_xlpm.project)*(TRIM(Sources!$D$2:$D$461)=_xlpm.attribute), Sources!$E$2:$E$461, "UNKNOWN" ) )} -> BVI | G13: {=_xlfn.LET( _xlpm.project,TRIM($C13), _xlpm.attribute,TRIM(IF(G$3<>"",G$3,G$2)), _xlfn.XLOOKUP( 1, (TRIM(Sources!$B$2:$B$461)=_xlpm.project)*(TRIM(Sources!$D$2:$D$461)=_xlpm.attribute), Sources!$E$2:$E$461, "UNKNOWN" ) )} -> Direct Issuer: Ltd. | H13: {=_xlfn.LET( _xlpm.project,TRIM($C13), _xlpm.attribute,TRIM(IF(H$3<>"",H$3,H$2)), _xlfn.XLOOKUP( 1, (TRIM(Sources!$B$2:$B$461)=_xlpm.project)*(TRIM(Sources!$D$2:$D$461)=_xlpm.attribute), Sources!$E$2:$E$461, "UNKNOWN" ) )} -> UNKNOWN | I13: {=_xlfn.LET( _xlpm.project,TRIM($C13), _xlpm.attribute,TRIM(IF(I$3<>"",I$3,I$2)), _xlfn.XLOOKUP( 1, (TRIM(Sources!$B$2:$B$461)=_xlpm.project)*(TRIM(Sources!$D$2:$D$461)=_xlpm.attribute), Sources!$E$2:$E$461, "UNKNOWN" ) )} -> Institutional custodian (regulated) | J13: {=_xlfn.LET( _xlpm.project,TRIM($C13), _xlpm.attribute,TRIM(IF(J$3<>"",J$3,J$2)), _xlfn.XLOOKUP( 1, (TRIM(Sources!$B$2:$B$461)=_xlpm.project)*(TRIM(Sources!$D$2:$D$461)=_xlpm.attribute), Sources!$E$2:$E$461, "UNKNOWN" ) )} -> SPV held | K13: {=_xlfn.LET( _xlpm.project,TRIM($C13), _xlpm.attribute,TRIM(IF(K$3<>"",K$3,K$2)), _xlfn.XLOOKUP( 1, (TRIM(Sources!$B$2:$B$461)=_xlpm.project)*(TRIM(Sources!$D$2:$D$461)=_xlpm.attribute), Sources!$E$2:$E$461, "UNKNOWN" ) )} -> UNKNOWN | L13: {=_xlfn.LET( _xlpm.project,TRIM($C13), _xlpm.attribute,TRIM(IF(L$3<>"",L$3,L$2)), _xlfn.XLOOKUP( 1, (TRIM(Sources!$B$2:$B$461)=_xlpm.project)*(TRIM(Sources!$D$2:$D$461)=_xlpm.attribute), Sources!$E$2:$E$461, "UNKNOWN" ) )} -> Pro-rata claim on asset (share of pooled underlying) | M13: {=_xlfn.LET( _xlpm.project,TRIM($C13), _xlpm.attribute,TRIM(IF(M$3<>"",M$3,M$2)), _xlfn.XLOOKUP( 1, (TRIM(Sources!$B$2:$B$461)=_xlpm.project)*(TRIM(Sources!$D$2:$D$461)=_xlpm.attribute), Sources!$E$2:$E$461, "UNKNOWN" ) )} -> Redemption right; Income distribution right; Interest entitlement | ... AB13: {=_xlfn.LET( _xlpm.project,TRIM($C13), _xlpm.attribute,TRIM(IF(AB$3<>"",AB$3,AB$2)), _xlfn.XLOOKUP( 1, (TRIM(Sources!$B$2:$B$461)=_xlpm.project)*(TRIM(Sources!$D$2:$D$461)=_xlpm.attribute), Sources!$E$2:$E$461, "UNKNOWN" ) )} -> Qualified investors only; pre-approved investors only; Securitize Markets subscription
B14: 11 | C14: Hastra PRIME (PRIME) | D14: 46143 | E14: 11 | F14: {=_xlfn.LET( _xlpm.project,TRIM($C14), _xlpm.attribute,TRIM(IF(F$3<>"",F$3,F$2)), _xlfn.XLOOKUP( 1, (TRIM(Sources!$B$2:$B$461)=_xlpm.project)*(TRIM(Sources!$D$2:$D$461)=_xlpm.attribute), Sources!$E$2:$E$461, "UNKNOWN" ) )} -> BVI | G14: {=_xlfn.LET( _xlpm.project,TRIM($C14), _xlpm.attribute,TRIM(IF(G$3<>"",G$3,G$2)), _xlfn.XLOOKUP( 1, (TRIM(Sources!$B$2:$B$461)=_xlpm.project)*(TRIM(Sources!$D$2:$D$461)=_xlpm.attribute), Sources!$E$2:$E$461, "UNKNOWN" ) )} -> Limited Liability Company | H14: {=_xlfn.LET( _xlpm.project,TRIM($C14), _xlpm.attribute,TRIM(IF(H$3<>"",H$3,H$2)), _xlfn.XLOOKUP( 1, (TRIM(Sources!$B$2:$B$461)=_xlpm.project)*(TRIM(Sources!$D$2:$D$461)=_xlpm.attribute), Sources!$E$2:$E$461, "UNKNOWN" ) )} -> UNKNOWN | I14: {=_xlfn.LET( _xlpm.project,TRIM($C14), _xlpm.attribute,TRIM(IF(I$3<>"",I$3,I$2)), _xlfn.XLOOKUP( 1, (TRIM(Sources!$B$2:$B$461)=_xlpm.project)*(TRIM(Sources!$D$2:$D$461)=_xlpm.attribute), Sources!$E$2:$E$461, "UNKNOWN" ) )} -> Trust arrangement (intra-group, non-independent) | J14: {=_xlfn.LET( _xlpm.project,TRIM($C14), _xlpm.attribute,TRIM(IF(J$3<>"",J$3,J$2)), _xlfn.XLOOKUP( 1, (TRIM(Sources!$B$2:$B$461)=_xlpm.project)*(TRIM(Sources!$D$2:$D$461)=_xlpm.attribute), Sources!$E$2:$E$461, "UNKNOWN" ) )} -> Beneficial Ownership | K14: {=_xlfn.LET( _xlpm.project,TRIM($C14), _xlpm.attribute,TRIM(IF(K$3<>"",K$3,K$2)), _xlfn.XLOOKUP( 1, (TRIM(Sources!$B$2:$B$461)=_xlpm.project)*(TRIM(Sources!$D$2:$D$461)=_xlpm.attribute), Sources!$E$2:$E$461, "UNKNOWN" ) )} -> UNKNOWN | L14: {=_xlfn.LET( _xlpm.project,TRIM($C14), _xlpm.attribute,TRIM(IF(L$3<>"",L$3,L$2)), _xlfn.XLOOKUP( 1, (TRIM(Sources!$B$2:$B$461)=_xlpm.project)*(TRIM(Sources!$D$2:$D$461)=_xlpm.attribute), Sources!$E$2:$E$461, "UNKNOWN" ) )} -> Pro-rata claim on asset (share of pooled underlying) | M14: {=_xlfn.LET( _xlpm.project,TRIM($C14), _xlpm.attribute,TRIM(IF(M$3<>"",M$3,M$2)), _xlfn.XLOOKUP( 1, (TRIM(Sources!$B$2:$B$461)=_xlpm.project)*(TRIM(Sources!$D$2:$D$461)=_xlpm.attribute), Sources!$E$2:$E$461, "UNKNOWN" ) )} -> Redemption right; Interest entitlement | ... AB14: {=_xlfn.LET( _xlpm.project,TRIM($C14), _xlpm.attribute,TRIM(IF(AB$3<>"",AB$3,AB$2)), _xlfn.XLOOKUP( 1, (TRIM(Sources!$B$2:$B$461)=_xlpm.project)*(TRIM(Sources!$D$2:$D$461)=_xlpm.attribute), Sources!$E$2:$E$461, "UNKNOWN" ) )} -> KYC gated
B15: 12 | C15: Franklin OnChain U.S. Government Money Fund (BENJI) | D15: 46143 | E15: 12 | F15: {=_xlfn.LET( _xlpm.project,TRIM($C15), _xlpm.attribute,TRIM(IF(F$3<>"",F$3,F$2)), _xlfn.XLOOKUP( 1, (TRIM(Sources!$B$2:$B$461)=_xlpm.project)*(TRIM(Sources!$D$2:$D$461)=_xlpm.attribute), Sources!$E$2:$E$461, "UNKNOWN" ) )} -> USA | G15: {=_xlfn.LET( _xlpm.project,TRIM($C15), _xlpm.attribute,TRIM(IF(G$3<>"",G$3,G$2)), _xlfn.XLOOKUP( 1, (TRIM(Sources!$B$2:$B$461)=_xlpm.project)*(TRIM(Sources!$D$2:$D$461)=_xlpm.attribute), Sources!$E$2:$E$461, "UNKNOWN" ) )} -> Bankruptcy remote vehicle: Trust | H15: {=_xlfn.LET( _xlpm.project,TRIM($C15), _xlpm.attribute,TRIM(IF(H$3<>"",H$3,H$2)), _xlfn.XLOOKUP( 1, (TRIM(Sources!$B$2:$B$461)=_xlpm.project)*(TRIM(Sources!$D$2:$D$461)=_xlpm.attribute), Sources!$E$2:$E$461, "UNKNOWN" ) )} -> Yes (noncumulative shareholder voting rights; special meetings for matters requiring shareholder approval) | I15: {=_xlfn.LET( _xlpm.project,TRIM($C15), _xlpm.attribute,TRIM(IF(I$3<>"",I$3,I$2)), _xlfn.XLOOKUP( 1, (TRIM(Sources!$B$2:$B$461)=_xlpm.project)*(TRIM(Sources!$D$2:$D$461)=_xlpm.attribute), Sources!$E$2:$E$461, "UNKNOWN" ) )} -> Institutional custodian (regulated) | J15: {=_xlfn.LET( _xlpm.project,TRIM($C15), _xlpm.attribute,TRIM(IF(J$3<>"",J$3,J$2)), _xlfn.XLOOKUP( 1, (TRIM(Sources!$B$2:$B$461)=_xlpm.project)*(TRIM(Sources!$D$2:$D$461)=_xlpm.attribute), Sources!$E$2:$E$461, "UNKNOWN" ) )} -> Direct title (token holder is legal owner) | K15: {=_xlfn.LET( _xlpm.project,TRIM($C15), _xlpm.attribute,TRIM(IF(K$3<>"",K$3,K$2)), _xlfn.XLOOKUP( 1, (TRIM(Sources!$B$2:$B$461)=_xlpm.project)*(TRIM(Sources!$D$2:$D$461)=_xlpm.attribute), Sources!$E$2:$E$461, "UNKNOWN" ) )} -> UNKNOWN | L15: {=_xlfn.LET( _xlpm.project,TRIM($C15), _xlpm.attribute,TRIM(IF(L$3<>"",L$3,L$2)), _xlfn.XLOOKUP( 1, (TRIM(Sources!$B$2:$B$461)=_xlpm.project)*(TRIM(Sources!$D$2:$D$461)=_xlpm.attribute), Sources!$E$2:$E$461, "UNKNOWN" ) )} -> Pro-rata claim on asset (share of pooled underlying) | M15: {=_xlfn.LET( _xlpm.project,TRIM($C15), _xlpm.attribute,TRIM(IF(M$3<>"",M$3,M$2)), _xlfn.XLOOKUP( 1, (TRIM(Sources!$B$2:$B$461)=_xlpm.project)*(TRIM(Sources!$D$2:$D$461)=_xlpm.attribute), Sources!$E$2:$E$461, "UNKNOWN" ) )} -> Redemption right; Income distribution right; Governance/voting | ... AB15: {=_xlfn.LET( _xlpm.project,TRIM($C15), _xlpm.attribute,TRIM(IF(AB$3<>"",AB$3,AB$2)), _xlfn.XLOOKUP( 1, (TRIM(Sources!$B$2:$B$461)=_xlpm.project)*(TRIM(Sources!$D$2:$D$461)=_xlpm.attribute), Sources!$E$2:$E$461, "UNKNOWN" ) )} -> KYC gated; Whitelisted only
... B23: 20 | C23: mF-ONE (MF-ONE) | D23: 46154 | E23: 20 | F23: {=_xlfn.LET( _xlpm.project,TRIM($C23), _xlpm.attribute,TRIM(IF(F$3<>"",F$3,F$2)), _xlfn.XLOOKUP( 1, (TRIM(Sources!$B$2:$B$461)=_xlpm.project)*(TRIM(Sources!$D$2:$D$461)=_xlpm.attribute), Sources!$E$2:$E$461, "UNKNOWN" ) )} -> Germany | G23: {=_xlfn.LET( _xlpm.project,TRIM($C23), _xlpm.attribute,TRIM(IF(G$3<>"",G$3,G$2)), _xlfn.XLOOKUP( 1, (TRIM(Sources!$B$2:$B$461)=_xlpm.project)*(TRIM(Sources!$D$2:$D$461)=_xlpm.attribute), Sources!$E$2:$E$461, "UNKNOWN" ) )} -> Direct Issuer: GmbH | H23: {=_xlfn.LET( _xlpm.project,TRIM($C23), _xlpm.attribute,TRIM(IF(H$3<>"",H$3,H$2)), _xlfn.XLOOKUP( 1, (TRIM(Sources!$B$2:$B$461)=_xlpm.project)*(TRIM(Sources!$D$2:$D$461)=_xlpm.attribute), Sources!$E$2:$E$461, "UNKNOWN" ) )} -> UNKNOWN | I23: {=_xlfn.LET( _xlpm.project,TRIM($C23), _xlpm.attribute,TRIM(IF(I$3<>"",I$3,I$2)), _xlfn.XLOOKUP( 1, (TRIM(Sources!$B$2:$B$461)=_xlpm.project)*(TRIM(Sources!$D$2:$D$461)=_xlpm.attribute), Sources!$E$2:$E$461, "UNKNOWN" ) )} -> UNKNOWN | J23: {=_xlfn.LET( _xlpm.project,TRIM($C23), _xlpm.attribute,TRIM(IF(J$3<>"",J$3,J$2)), _xlfn.XLOOKUP( 1, (TRIM(Sources!$B$2:$B$461)=_xlpm.project)*(TRIM(Sources!$D$2:$D$461)=_xlpm.attribute), Sources!$E$2:$E$461, "UNKNOWN" ) )} -> N/A | K23: {=_xlfn.LET( _xlpm.project,TRIM($C23), _xlpm.attribute,TRIM(IF(K$3<>"",K$3,K$2)), _xlfn.XLOOKUP( 1, (TRIM(Sources!$B$2:$B$461)=_xlpm.project)*(TRIM(Sources!$D$2:$D$461)=_xlpm.attribute), Sources!$E$2:$E$461, "UNKNOWN" ) )} -> UNKNOWN | L23: {=_xlfn.LET( _xlpm.project,TRIM($C23), _xlpm.attribute,TRIM(IF(L$3<>"",L$3,L$2)), _xlfn.XLOOKUP( 1, (TRIM(Sources!$B$2:$B$461)=_xlpm.project)*(TRIM(Sources!$D$2:$D$461)=_xlpm.attribute), Sources!$E$2:$E$461, "UNKNOWN" ) )} -> Debt Instrument (Claim as a creditor) | M23: {=_xlfn.LET( _xlpm.project,TRIM($C23), _xlpm.attribute,TRIM(IF(M$3<>"",M$3,M$2)), _xlfn.XLOOKUP( 1, (TRIM(Sources!$B$2:$B$461)=_xlpm.project)*(TRIM(Sources!$D$2:$D$461)=_xlpm.attribute), Sources!$E$2:$E$461, "UNKNOWN" ) )} -> Redemption right | ... AB23: {=_xlfn.LET( _xlpm.project,TRIM($C23), _xlpm.attribute,TRIM(IF(AB$3<>"",AB$3,AB$2)), _xlfn.XLOOKUP( 1, (TRIM(Sources!$B$2:$B$461)=_xlpm.project)*(TRIM(Sources!$D$2:$D$461)=_xlpm.attribute), Sources!$E$2:$E$461, "UNKNOWN" ) )} -> Qualified investors only; KYC gated; Whitelisted only

Sheet Sources
A1: ID | B1: System | C1: Component | D1: Attribute | E1: Characteristic/ Value | F1: Reason | G1: Date of classification / access of docs (YYYY-MM-DD) | H1: Source Type (Official, on chain data, third party, regulatory finding ...) | I1: Confidence level | J1: text/info from link | K1: links:
A2: 1 | B2: Tether Gold (XAUt) | C2: Governance | D2: Incorporation Jurisdiction | E2: El Salvador | F2: Issuer is incorporated under El Salvador law. | G2: 46112 | H2: Official | I2: High | J2: a company incorporated and in effect under the Laws of El Salvador | K2: https://gold.tether.to/Relevant%20Information%20Document%20-%20TG%20Commodities%2C%20S.A.%20de%20C.V.%20%28ENG%29.pdf
B3: Tether Gold (XAUt) | C3: Governance | D3: Legal Entity (Wrapper) | E3: Direct Issuer: SA de C.V. | F3: TG Commodities is the issuing and redeeming entity. | G3: 46112 | H3: Official | I3: High | J3: TG Commodities is the customer-facing entity that issues and redeems Tether Gold Tokens | K3: https://gold.tether.to/Relevant%20Information%20Document%20-%20TG%20Commodities%2C%20S.A.%20de%20C.V.%20%28ENG%29.pdf
B4: Tether Gold (XAUt) | C4: Governance | D4: Voting | E4: N/A | F4: The official RID describes XAUt as an issuer-managed, gold-backed ERC-20 token and does not disclose any token-holder governance or voting mechanism. | G4: 46139 | H4: Official documentation | I4: Medium | J4: RID: each token represents an interest in one fine troy ounce of LBMA gold; TG Commodities issues/redeems; XAUt is ERC-20 on Ethereum. No voting or governance voting process is disclosed in the reviewed official source. | K4: https://gold.tether.to/Relevant%20Information%20Document%20-%20TG%20Commodities%2C%20S.A.%20de%20C.V.%20%28ENG%29.pdf
B5: Tether Gold (XAUt) | C5: Asset | D5: Custody Arrangement | E5: Vault storage (physical assets) | F5: Gold reserves are stored in a Swiss vault. | G5: 46112 | H5: Official | I5: High | J5: The Gold Reserves are held by the custodian in a vault in Switzerland | K5: https://gold.tether.to/Relevant%20Information%20Document%20-%20TG%20Commodities%2C%20S.A.%20de%20C.V.%20%28ENG%29.pdf
B6: Tether Gold (XAUt) | C6: Asset | D6: Ownership Structure | E6: Beneficial ownership (custodian holds legal title on behalf of user) | F6: Gold reserves are held by a custodian on behalf of holders. | G6: 46112 | H6: Official | I6: High | J6: the Gold Reserves are held by a custodian on behalf of XAU₮ holders | K6: https://gold.tether.to/Relevant%20Information%20Document%20-%20TG%20Commodities%2C%20S.A.%20de%20C.V.%20%28ENG%29.pdf
B7: Tether Gold (XAUt) | C7: Asset | D7: Dispute Forum | E7: CPR Arbitration; BVI law | F7: RID states BVI law and CPR arbitration. | G7: 46112 | H7: Official | I7: High | J7: shall be governed by the Laws of the BVI and will be subject to and finally resolved by confidential, binding arbitration | K7: https://gold.tether.to/Relevant%20Information%20Document%20-%20TG%20Commodities%2C%20S.A.%20de%20C.V.%20%28ENG%29.pdf
B8: Tether Gold (XAUt) | C8: Asset | D8: Claim Type | E8: Direct Claim on asset | F8: Each token represents ownership of one fine troy ounce on a specific bar. | G8: 46112 | H8: Official | I8: High | J8: represent ownership of an undivided specific interest in one fine troy ounce of gold | K8: https://gold.tether.to/Relevant%20Information%20Document%20-%20TG%20Commodities%2C%20S.A.%20de%20C.V.%20%28ENG%29.pdf
B9: Tether Gold (XAUt) | C9: Asset | D9: Entitlements | E9: Redemption right | F9: Verified customers can redeem for physical delivery or sale proceeds. | G9: 46112 | H9: Official | I9: High | J9: If a KYC Verified Customer wishes to redeem their Tether Gold Tokens | K9: https://gold.tether.to/Relevant%20Information%20Document%20-%20TG%20Commodities%2C%20S.A.%20de%20C.V.%20%28ENG%29.pdf
B10: Tether Gold (XAUt) | C10: Asset | D10: Asset Type | E10: Commodity (GOLD) | F10: Underlying asset is physical gold. | G10: 46112 | H10: Official | I10: High | J10: one fine troy ounce of gold | K10: https://gold.tether.to/Relevant%20Information%20Document%20-%20TG%20Commodities%2C%20S.A.%20de%20C.V.%20%28ENG%29.pdf
B11: Tether Gold (XAUt) | C11: Asset | D11: Third-Party Audit | E11: Yes; quarterly; https://tether.to/en/transparency | F11: RID says gold reserve reports and independent auditors’ reports are prepared quarterly. | G11: 46112 | H11: Official | I11: High | J11: we will publish reports on the Gold Reserves quarterly | K11: https://gold.tether.to/Relevant%20Information%20Document%20-%20TG%20Commodities%2C%20S.A.%20de%20C.V.%20%28ENG%29.pdf
B12: Tether Gold (XAUt) | C12: Asset | D12: On-Chain Proof | E12: other | F12: Tether Gold describes XAUt as a tokenized claim on allocated physical gold, with an issuer-run “Look-up Website” that maps on-chain addresses to specific gold bars, plus periodic reserve attestations, no on chain PoR | G12: 46112 | H12: Official | I12: Medium | J12: we will publish reports on the Gold Reserves quarterly, that will be available on the Tether’s Transparency page https://tether.to/en/transparency (the “Transparency Page”). In addition, Independent Auditors’ Reports on those Gold Reserve reports will be prepared by an independent third party accounting rm, | K12: https://gold.tether.to/Relevant%20Information%20Document%20-%20TG%20Commodities%2C%20S.A.%20de%20C.V.%20%28ENG%29.pdf
B13: Tether Gold (XAUt) | C13: Token Properties | D13: Divisibility | E13: Fractionalized | F13: XAUt can be divided to six decimal places. | G13: 46112 | H13: Official | I13: High | J13: can be fractionalized up to six decimal places | K13: https://gold.tether.to/Relevant%20Information%20Document%20-%20TG%20Commodities%2C%20S.A.%20de%20C.V.%20%28ENG%29.pdf
B14: Tether Gold (XAUt) | C14: Token Properties | D14: Settlement Form(s) | E14: Combination | F14: Redemption can settle as physical delivery or sale proceeds in USD. | G14: 46112 | H14: Official | I14: High | J14: physical delivery of the underlying full gold bar in Switzerland, or may request that Tether Gold attempt to sell their bullion bar | K14: https://gold.tether.to/Relevant%20Information%20Document%20-%20TG%20Commodities%2C%20S.A.%20de%20C.V.%20%28ENG%29.pdf
... B24: Tether Gold (XAUt) | C24: Economy | D24: Primary Market Access | E24: KYC gated | F24: Direct purchases and redemptions require successful KYC verification. | G24: 46112 | H24: Official | I24: High | J24: KYC Verified Customers can purchase and redeem Tether Gold Tokens directly through the Tether Gold Website | K24: https://gold.tether.to/Relevant%20Information%20Document%20-%20TG%20Commodities%2C%20S.A.%20de%20C.V.%20%28ENG%29.pdf
A25: 2 | B25: BUIDL | C25: Governance | D25: Incorporation Jurisdiction | E25: BVI | F25: SEC Form D lists the issuer as incorporated in the British Virgin Islands. | G25: 46112 | H25: Regulatory finding | I25: High | J25: Jurisdiction of Incorporation/Organization VIRGIN ISLANDS, BRITISH | K25: https://www.sec.gov/Archives/edgar/data/2013810/000201439024000001/xslFormDX01/primary_doc.xml
B26: BUIDL | C26: Governance | D26: Legal Entity (Wrapper) | E26: Direct Issuer: Ltd. | F26: SEC filing identifies the issuing entity as a limited company. | G26: 46112 | H26: Regulatory finding | I26: High | J26: Entity Type ... Other (Specify) Limited Company | K26: https://www.sec.gov/Archives/edgar/data/2013810/000201439024000001/xslFormDX01/primary_doc.xml
B27: BUIDL | C27: Governance | D27: Voting | E27: No token-holder voting system identified for the tokenized fund; BUIDL is not DAO-governed. | F27: The fund shares are described as non-voting participating Class A Shares issued as digital tokens; a risk assessment states BUIDL is not subject to DAO governance. | G27: 46139 | H27: Third-party risk assessment; official/regulatory context | I27: High | J27: Aave/LlamaRisk: BUIDL presents non-voting, participating Class A Shares issued as digital tokens; BUIDL is not subject to DAO governance. SEC Form D identifies the issuer as BlackRock USD Institutional Digital Liquidity Fund Ltd. | K27: https://governance.aave.com/t/arfc-ustb-buidl-gsm/19299 https://www.sec.gov/Archives/edgar/data/2013810/000201439024000001/xslFormDX01/primary_doc.xml
B28: BUIDL | C28: Asset | D28: Custody Arrangement | E28: Institutional custodian (regulated) | F28: BNY Mellon is named as custodian. | G28: 46112 | H28: Official | I28: High | J28: Bank of New York Mellon will serve as the custodian of the Fund's assets and its administrator | K28: https://www.businesswire.com/news/home/20240320771318/en/BlackRock-Launches-Its-First-Tokenized-Fund-BUIDL-on-the-Ethereum-Network
B29: BUIDL | C29: Asset | D29: Ownership Structure | E29: Beneficial ownership (custodian holds legal title on behalf of user) | F29: Investors hold tokenized fund shares while the underlying fund assets are custodied by BNY Mellon. | G29: 46112 | H29: Official | I29: Medium | J29: Bank of New York Mellon will serve as the custodian of the Fund's assets ... Securitize will act as a transfer agent and tokenization platform, managing the tokenized shares | K29: https://www.businesswire.com/news/home/20240320771318/en/BlackRock-Launches-Its-First-Tokenized-Fund-BUIDL-on-the-Ethereum-Network
B30: BUIDL | C30: Asset | D30: Dispute Forum | E30: Delaware, Disputes resolved in New York | F30: Rule of law: Delaware. Disputes are to be resolved by the Supreme Court of the State of New York | G30: 46112 | H30: Third party | I30: Medium | J30: Dispute Resolution Country Delaware | K30: https://forum.arbitrum.foundation/t/securitize-markets-buidl-step-application/23652
B31: BUIDL | C31: Asset | D31: Claim Type | E31: Pro-rata claim on asset (share of pooled underlying) | F31: The security offered is a pooled fund interest represented as tokenized shares. | G31: 46112 | H31: Regulatory finding | I31: Medium | J31: Type(s) of Securities Offered ... Pooled Investment Fund Interests | K31: https://www.sec.gov/Archives/edgar/data/2013810/000201439024000001/xslFormDX01/primary_doc.xml
B32: BUIDL | C32: Asset | D32: Entitlements | E32: Redemption right; Income distribution right | F32: Official materials disclose both distributions and redemptions. | G32: 46112 | H32: Official | I32: High | J32: reporting on Fund subscriptions, redemptions, and distributions | K32: https://www.businesswire.com/news/home/20240320771318/en/BlackRock-Launches-Its-First-Tokenized-Fund-BUIDL-on-the-Ethereum-Network
B33: BUIDL | C33: Asset | D33: Asset Type | E33: Fixed income (government/corporate bonds) | F33: The underlying exposure is U.S. Treasury debt and repo. | G33: 46112 | H33: Official | I33: High | J33: The Fund invests 100% of its total assets in cash, U.S. Treasury bills, and repurchase agreements | K33: https://www.businesswire.com/news/home/20240320771318/en/BlackRock-Launches-Its-First-Tokenized-Fund-BUIDL-on-the-Ethereum-Network
B34: BUIDL | C34: Asset | D34: Third-Party Audit | E34: Yes; annual by PwC | F34: PwC is appointed as auditor for the year-end period. | G34: 46112 | H34: Official | I34: High | J34: Auditor: PwC | K34: https://app.rwa.xyz/assets/BUIDL
B35: BUIDL | C35: Asset | D35: On-Chain Proof | E35: UNKNOWN | F35: No explicit proof-of-reserves or similar on-chain proof mechanism was identified in the reviewed materials. | G35: 46112 | H35: Official | I35: Low | J35: providing instantaneous and transparent settlement | K35: https://www.businesswire.com/news/home/20240320771318/en/BlackRock-Launches-Its-First-Tokenized-Fund-BUIDL-on-the-Ethereum-Network
B36: BUIDL | C36: Token Properties | D36: Divisibility | E36: Fractionalized | F36: Token supply is shown with decimal precision. | G36: 46112 | H36: Third party | I36: Medium | J36: Token Supply 1,998,788,657.94 | K36: https://app.rwa.xyz/assets/BUIDL
B37: BUIDL | C37: Token Properties | D37: Settlement Form(s) | E37: Combination | F37: Primary-market base assets include both fiat and stablecoin rails. | G37: 46112 | H37: Third party | I37: Medium | J37: Base Assets USDC USD | K37: https://app.rwa.xyz/assets/BUIDL
... B47: BUIDL | C47: Economy | D47: Primary Market Access | E47: Qualified investors only | F47: Official launch materials limit direct participation to qualified investors. | G47: 46112 | H47: Official | I47: High | J47: BUIDL will provide qualified investors with the opportunity to earn U.S. dollar yields by subscribing to the Fund through Securitize Markets, LLC | K47: https://www.businesswire.com/news/home/20240320771318/en/BlackRock-Launches-Its-First-Tokenized-Fund-BUIDL-on-the-Ethereum-Network
A48: 3 | B48: PAX Gold | C48: Governance | D48: Incorporation Jurisdiction | E48: USA | F48: Issuer is a U.S. national banking association. | G48: 46113 | H48: Official | I48: High | J48: Paxos Trust Company, NA, a national banking association organized under the laws of the United States | K48: https://www.paxos.com/terms-and-conditions/general-terms-and-conditions
B49: PAX Gold | C49: Governance | D49: Legal Entity (Wrapper) | E49: Direct Issuer: N.A. | F49: PAX Gold is managed by Paxos Trust Company, N.A. | G49: 46113 | H49: Official | I49: High | J49: gold denominated and backed token managed by Paxos Trust Company, NA | K49: https://www.paxos.com/terms-and-conditions/pax-gold-terms-conditions
B50: PAX Gold | C50: Governance | D50: Voting | E50: No voting system identified. | F50: Official PAXG terms describe asset ownership, ERC-20 transferability, conversion and Paxos control rights; no holder governance or voting system is disclosed. | G50: 46139 | H50: Official documentation | I50: Medium | J50: PAXG terms: PAXG can be transferred, traded, kept, used for payment, or converted with Paxos; each token equals one fine troy ounce of London Good Delivery gold. No governance voting process is disclosed in the reviewed terms. | K50: https://www.paxos.com/terms-and-conditions/pax-gold-terms-conditions
B51: PAX Gold | C51: Asset | D51: Custody Arrangement | E51: Vault storage (physical assets) | F51: Backing gold is stored in LBMA vaults in London. | G51: 46113 | H51: Official | I51: High | J51: Each Pax Gold (PAXG) token is backed by one fine troy ounce of gold, stored in LBMA vaults in London | K51: https://www.paxos.com/pax-gold
B52: PAX Gold | C52: Asset | D52: Ownership Structure | E52: Beneficial ownership (custodian holds legal title on behalf of user) | F52: Terms describe beneficial ownership of allocated gold rather than direct legal title. | G52: 46113 | H52: Official | I52: High | J52: you will become the beneficial owner of those tokens and the underlying allocated gold | K52: https://www.paxos.com/terms-and-conditions/pax-gold-terms-conditions
B53: PAX Gold | C53: Asset | D53: Dispute Forum | E53: Binding arbitration; New York law | F53: Disputes involving Paxos Trust customers are arbitrated in New York under New York law. | G53: 46113 | H53: Official | I53: High | J53: customers of Paxos Trust by arbitration in New York, New York ... governed by the laws of the State of New York | K53: https://www.paxos.com/terms-and-conditions/general-terms-and-conditions
B54: PAX Gold | C54: Asset | D54: Claim Type | E54: Pro-rata claim on asset (share of pooled underlying) | F54: Terms characterize PAXG as a warehouse receipt for a pro-rata portion of allocated gold. | G54: 46113 | H54: Official | I54: High | J54: representing your beneficial ownership of a pro rata portion of Allocated Gold | K54: https://www.paxos.com/terms-and-conditions/pax-gold-terms-conditions
B55: PAX Gold | C55: Asset | D55: Entitlements | E55: Redemption right | F55: Holders can convert or redeem PAXG into USD, unallocated gold, or allocated gold. | G55: 46113 | H55: Official | I55: High | J55: convert PAXG for US dollars, Unallocated Gold, and Allocated Gold | K55: https://www.paxos.com/terms-and-conditions/pax-gold-terms-conditions
B56: PAX Gold | C56: Asset | D56: Asset Type | E56: Commodity (GOLD) | F56: Underlying asset is physical gold. | G56: 46113 | H56: Official | I56: High | J56: Each PAXG token is equal to one fine troy ounce of London Good Delivery gold | K56: https://www.paxos.com/terms-and-conditions/pax-gold-terms-conditions
B57: PAX Gold | C57: Asset | D57: Third-Party Audit | E57: Yes; monthly; https://www.paxos.com/paxg-transparency | F57: Paxos publishes monthly attestation reports from an independent accounting firm. | G57: 46113 | H57: Official | I57: High | J57: Paxos publishes attestation reports each month | K57: https://www.paxos.com/paxg-transparency
B58: PAX Gold | C58: Asset | D58: On-Chain Proof | E58: Other (Lookup tool) | F58: Paxos provides an address-based gold allocation lookup tool rather than a standard proof-of-reserves oracle. | G58: 46113 | H58: Official | I58: High | J58: Use this tool to lookup the serial number and information about your gold | K58: https://www.paxos.com/pax-gold
B59: PAX Gold | C59: Token Properties | D59: Divisibility | E59: Fractionalized | F59: Official materials explicitly state fractional ownership of physical bars. | G59: 46113 | H59: Official | I59: High | J59: Customers are able to have fractional ownership of physical bars. Page 8 Whitepaper | K59: https://www.paxos.com/pax-gold
B60: PAX Gold | C60: Token Properties | D60: Settlement Form(s) | E60: Combination | F60: PAXG can be redeemed into USD, unallocated gold, or allocated gold. | G60: 46113 | H60: Official | I60: High | J60: convert PAXG for US dollars, Unallocated Gold, and Allocated Gold | K60: https://www.paxos.com/terms-and-conditions/pax-gold-terms-conditions
... B70: PAX Gold | C70: Economy | D70: Primary Market Access | E70: KYC gated | F70: Direct primary-market purchase, conversion, and redemption are limited to verified customers. | G70: 46113 | H70: Official | I70: High | J70: Only verified Customers may purchase PAXG from us or convert or redeem PAXG from us | K70: https://www.paxos.com/terms-and-conditions/pax-gold-terms-conditions
A71: 4 | B71: US Yield Coin (UYSC) | C71: Governance | D71: Incorporation Jurisdiction | E71: Bermuda | F71: Official docs identify the issuer as Circle International Bermuda Limited and regulated by BMA. | G71: 46139 | H71: Official | I71: High | J71: issued by Circle International Bermuda Limited, regulated by Bermuda Monetary Authority | K71: https://usyc.docs.hashnote.com/
B72: US Yield Coin (UYSC) | C72: Governance | D72: Legal Entity (Wrapper) | E72: Direct Issuer: Ltd. | F72: Official docs identify Circle International Bermuda Limited as issuer. | G72: 46139 | H72: Official | I72: High | J72: USYC is issued by Circle International Bermuda Limited | K72: https://usyc.docs.hashnote.com/overview/product-structuring
B73: US Yield Coin (UYSC) | C73: Governance | D73: Voting | E73: UNKNOWN | F73: No explicit tokenholder voting system was found in reviewed official USYC docs. | G73: 46139 | H73: Official | I73: Low | J73: No explicit voting-system statement located in reviewed official documentation.
B74: US Yield Coin (UYSC) | C74: Asset | D74: Custody Arrangement | E74: Institutional custodian (regulated) | F74: Assets are held through segregated custodial accounts at the prime broker; official docs also list regulated issuer/fund context. | G74: 46139 | H74: Official | I74: Medium | J74: Assets are protected through segregated custodial accounts at our prime broker | K74: https://usyc.docs.hashnote.com/
B75: US Yield Coin (UYSC) | C75: Asset | D75: Ownership Structure | E75: Beneficial ownership (custodian holds legal title on behalf of user) | F75: Token holders are represented in the SDYF share registry while assets are held through the fund structure. | G75: 46139 | H75: Official | I75: Medium | J75: Ownership in SDYF is represented as shares at the Transfer Agent | K75: https://usyc.docs.hashnote.com/overview/product-structuring
B76: US Yield Coin (UYSC) | C76: Asset | D76: Dispute Forum | E76: UNKNOWN | F76: No explicit governing-law or dispute-forum clause was found in reviewed official USYC docs. | G76: 46139 | H76: Official | I76: Low | J76: No explicit dispute-forum statement located in reviewed official documentation. | K76: https://usyc.docs.hashnote.com/
B77: US Yield Coin (UYSC) | C77: Asset | D77: Claim Type | E77: Pro-rata claim on asset (share of pooled underlying) | F77: Tokens represent shares in the pooled SDYF fund. | G77: 46139 | H77: Official | I77: High | J77: Tokens represent shares in the fund | K77: https://usyc.docs.hashnote.com/overview/product-structuring
B78: US Yield Coin (UYSC) | C78: Asset | D78: Entitlements | E78: Redemption right; Interest entitlement | F78: Docs disclose redemption into USDC and short-term Fed-rate returns. | G78: 46139 | H78: Official | I78: High | J78: redeem USYC into USDC; USYC earns short-term Fed rate returns | K78: https://usyc.docs.hashnote.com/overview/subscription-and-redemption and https://usyc.docs.hashnote.com/
B79: US Yield Coin (UYSC) | C79: Asset | D79: Asset Type | E79: Fixed income (government/corporate bonds) | F79: Underlying assets are short-term U.S. Treasury bills and repo/reverse-repo activity. | G79: 46139 | H79: Official | I79: High | J79: invests in short-term US Treasury Bills and performs repo / reverse-repo activity | K79: https://usyc.docs.hashnote.com/
B80: US Yield Coin (UYSC) | C80: Asset | D80: Third-Party Audit | E80: Yes; frequency UNKNOWN; https://usyc.docs.hashnote.com/overview/service-providers | F80: Official service-provider page lists Cohen and Company as auditor, but no audit frequency is stated there. | G80: 46139 | H80: Official | I80: Medium | J80: Auditor | Cohen and Company | K80: https://usyc.docs.hashnote.com/overview/service-providers
B81: US Yield Coin (UYSC) | C81: Asset | D81: On-Chain Proof | E81: Smart contract oracle feed | F81: Official docs state assets/token prices are published through an oracle feed. | G81: 46139 | H81: Official | I81: High | J81: Assets and token prices are regularly published via an Oracle feed | K81: https://usyc.docs.hashnote.com/
B82: US Yield Coin (UYSC) | C82: Token Properties | D82: Divisibility | E82: Fractionalized | F82: On-chain token page reports six decimals. | G82: 46139 | H82: On chain data | I82: Medium | J82: Token Contract (WITH 6 Decimals) | K82: https://etherscan.io/token/0x136471a34f6ef19fE571EFFC1CA711fdb8E49f2b
B83: US Yield Coin (UYSC) | C83: Token Properties | D83: Settlement Form(s) | E83: In-kind (other token) | F83: Redemption settles into USDC, another token. | G83: 46139 | H83: Official | I83: High | J83: redeem USYC into USDC | K83: https://usyc.docs.hashnote.com/overview/subscription-and-redemption
B84: US Yield Coin (UYSC) | C84: Token Properties | D84: Burn | E84: Yes | F84: Redemption workflow burns USYC. | G84: 46139 | H84: Official | I84: High | J84: burn your USYC and receive USDC
B85: US Yield Coin (UYSC) | C85: Token Properties | D85: Transferability | E85: Whitelist-restricted | F85: Holding and transfers require allowlist/permissioned-wallet roles. | G85: 46139 | H85: Official | I85: High | J85: wallet address is added to the Allowlist | K85: https://usyc.docs.hashnote.com/overview/product-structuring
B86: US Yield Coin (UYSC) | C86: DLT | D86: Chain Deployment | E86: Ethereum; BSC; Solana | F86: Official smart-contract page lists mainnet deployments on Ethereum, BSC, and Solana. | G86: 46139 | H86: Official | I86: High | J86: Ethereum | USYC ERC20 Token; BSC | USYC BEP20 Token; Solana | USYC SPL22 Token | K86: https://usyc.docs.hashnote.com/overview/smart-contracts
B87: US Yield Coin (UYSC) | C87: Token Properties | D87: Source of Yield | E87: Interest income | F87: Yield comes from Treasury bills and repo/reverse-repo activity. | G87: 46139 | H87: Official | I87: High | J87: USYC earns short-term Fed rate returns | K87: https://usyc.docs.hashnote.com/
B88: US Yield Coin (UYSC) | C88: Token Properties | D88: Yield Distribution Method | E88: Accrual | F88: Yield is reflected through NAV/token price rather than token-count increases. | G88: 46139 | H88: Official | I88: High | J88: price is calculated based on the Net Asset Value (NAV) | K88: https://usyc.docs.hashnote.com/overview/token-price
B89: US Yield Coin (UYSC) | C89: Token Properties | D89: Supply | E89: UNKNOWN | F89: No explicit capped or uncapped supply statement was found in reviewed official USYC docs. | G89: 46139 | H89: Official | I89: Low | J89: No explicit token supply cap statement located in reviewed official documentation. | K89: https://usyc.docs.hashnote.com/overview/smart-contracts
B90: US Yield Coin (UYSC) | C90: DLT | D90: DeFi Integrations | E90: Collateral | F90: Official docs mention composability but do not verify a specific taxonomy-aligned DeFi integration. | G90: 46139 | H90: Official | I90: High | J90: yield-bearing cross-margin collateral option. Available to all Deribit users starting October 8, 2024 | K90: https://insights.deribit.com/exchange-updates/deribit-introduces-hashnotes-usyc-as-new-yield-bearing-cross-margin-collateral-option/
B91: US Yield Coin (UYSC) | C91: DLT | D91: Smart Contract | E91: Minting/subscription; redemption/burn; transfer permissioning; oracle price reporting | F91: Core subscription, redemption, permissioning, and oracle functions are implemented by smart contracts. | G91: 46139 | H91: Official | I91: High | J91: USYC Token; Teller; Oracle; Entitlements | K91: https://usyc.docs.hashnote.com/overview/smart-contracts
B92: US Yield Coin (UYSC) | C92: Economy | D92: Protocol fees | E92: Minting Fee; Redemption Fee; Yield Spread | F92: Official fee schedule lists subscription, redemption, and performance fees. | G92: 46139 | H92: Official | I92: High | J92: Performance Fee; Subscription Fee; Redemption Fee | K92: https://usyc.docs.hashnote.com/overview/fees
B93: US Yield Coin (UYSC) | C93: Economy | D93: Primary Market Access | E93: Institutional only; KYC gated; Whitelisted only | F93: Primary access is limited to institutions outside the U.S. after onboarding, KYC/AML, and wallet whitelisting. | G93: 46139 | H93: Official | I93: High | J93: only accessible to institutions outside the United States | K93: https://usyc.docs.hashnote.com/overview/investor-onboarding
A94: 5 | B94: Superstate USTB | C94: Governance | D94: Incorporation Jurisdiction | E94: USA | F94: Official docs identify the Fund as a series of a Delaware statutory trust; Superstate's product page lists United States domicile. | G94: 46139 | H94: Official | I94: High | J94: The Fund is organized as a series of Superstate Asset Trust, a Delaware statutory trust; Domicile | United States | K94: https://docs.superstate.com/superstate-funds/ustb/legal-structure
B95: Superstate USTB | C95: Governance | D95: Legal Entity (Wrapper) | E95: Bankruptcy remote vehicle: Trust | F95: Official legal structure describes a Delaware Statutory Trust and states the Fund is bankruptcy remote from Superstate Advisers LLC. | G95: 46139 | H95: Official | I95: High | J95: The Delaware Statutory Trust structure means the shareholder's investment in the Fund is in a separate legal entity which is bankruptcy remote
B96: Superstate USTB | C96: Governance | D96: Voting | E96: UNKNOWN | F96: No explicit tokenholder voting system was found in reviewed official USTB docs. | G96: 46139 | H96: Official | I96: Low | J96: No explicit voting-system statement located in reviewed official documentation.
B97: Superstate USTB | C97: Asset | D97: Custody Arrangement | E97: Institutional custodian (regulated) | F97: Official Superstate product page lists The Bank of New York Mellon as custodian. | G97: 46139 | H97: Official | I97: High | J97: Custodian | The Bank of New York Mellon | K97: https://superstate.com/assets/ustb
B98: Superstate USTB | C98: Asset | D98: Ownership Structure | E98: SPV held | F98: Official docs state the shareholder's investment is in the Fund as a separate legal entity and that ownership in the Fund is represented by USTB. | G98: 46139 | H98: Official | I98: High | J98: shareholder's investment in the Fund is in a separate legal entity; Ownership in the Fund is represented by USTB | K98: https://docs.superstate.com/superstate-funds/ustb/legal-structure
B99: Superstate USTB | C99: Asset | D99: Dispute Forum | E99: UNKNOWN | F99: Official Superstate documentation identifies USTB as a Delaware statutory trust series, but no explicit dispute forum/arbitration venue was located in the public official documentation reviewed. | G99: 2026-05-12 | H99: Official documentation | I99: Low | J99: The Fund is organized as a series of Superstate Asset Trust, a Delaware statutory trust. | K99: https://docs.superstate.com/superstate-funds/ustb/legal-structure
B100: Superstate USTB | C100: Asset | D100: Claim Type | E100: Pro-rata claim on asset (share of pooled underlying) | F100: USTB represents ownership in shares of a pooled fund holding short-duration U.S. government securities. | G100: 46139 | H100: Official | I100: High | J100: Ownership in the Fund is represented by USTB, held either as a token or in book-entry record keeping. | K100: https://superstate.com/assets/ustb
B101: Superstate USTB | C101: Asset | D101: Entitlements | E101: Redemption right; Interest entitlement | F101: Docs state holders can redeem holdings and that interest income is reflected in NAV. | G101: 46139 | H101: Official | I101: High | J101: you can redeem the full amount of your holdings at any time; Interest income from these securities is recognized each market day | K101: https://docs.superstate.com/superstate-funds/ustb/redeeming-ustb
B102: Superstate USTB | C102: Asset | D102: Asset Type | E102: Fixed income (government/corporate bonds) | F102: Official docs state the Fund invests in short-duration U.S. Treasury Bills and U.S. Government Securities. | G102: 46139 | H102: Official | I102: High | J102: invests exclusively in short-duration U.S. Government Securities, including investments in U.S. Treasury Bills | K102: https://docs.superstate.com/superstate-funds/ustb/income-fees-and-yield
B103: Superstate USTB | C103: Asset | D103: Third-Party Audit | E103: Yes; annual; https://superstate.com/assets/ustb | F103: Official product page lists Ernst & Young LLP as auditor and legal docs state audited financial statements are provided after year end. | G103: 46139 | H103: Official | I103: High | J103: Auditor | Ernst & Young LLP; After the end of a calendar year, audited financial statements and K-1s will be provided | K103: https://superstate.com/assets/ustb
B104: Superstate USTB | C104: Asset | D104: On-Chain Proof | E104: Smart contract oracle feed | F104: Official smart-contract docs disclose continuous and Chainlink oracle feeds for NAV/S pricing. | G104: 46139 | H104: Official | I104: High | J104: Chainlink puts the USTB/USCC Net Asset Value per Share price onchain once per day | K104: https://docs.superstate.com/welcome-to-superstate/smart-contracts
B105: Superstate USTB | C105: Token Properties | D105: Divisibility | E105: Fractionalized | F105: Official product data shows fractional USTB share amounts and docs record NAV/S to six decimals. | G105: 46139 | H105: Official | I105: Medium | J105: 77,322,742.01 USTB; The NAV/S of USTB is recorded with 6 decimal places of accuracy | K105: https://superstate.com/assets/ustb
B106: Superstate USTB | C106: Token Properties | D106: Settlement Form(s) | E106: Combination | F106: Redemption proceeds may be delivered as U.S. dollars or USDC. | G106: 46139 | H106: Official | I106: High | J106: Proceeds from a redemption may be delivered as U.S. Dollars or USDC on select networks | K106: https://docs.superstate.com/superstate-funds/ustb/redeeming-ustb
B107: Superstate USTB | C107: Token Properties | D107: Burn | E107: Yes | F107: On-chain redemption burns USTB from the investor wallet in exchange for USDC. | G107: 46139 | H107: Official | I107: High | J107: Investors can call the redeem function on the contract to burn USTB from the investor's wallet and receive USDC | K107: https://docs.superstate.com/welcome-to-superstate/smart-contracts
B108: Superstate USTB | C108: Token Properties | D108: Transferability | E108: Whitelist-restricted | F108: Official docs state transfers are allowed only between allowlisted addresses. | G108: 46139 | H108: Official | I108: High | J108: USTB is freely transferable between wallet addresses on the Allowlist | K108: https://docs.superstate.com/superstate-funds/ustb
B109: Superstate USTB | C109: DLT | D109: Chain Deployment | E109: Ethereum; Solana; Plume | F109: Official docs and product page list USTB on Ethereum, Solana, and Plume. | G109: 46139 | H109: Official | I109: High | J109: Shares of the Fund are issued as USTB tokens on Ethereum, Solana, and Plume
B110: Superstate USTB | C110: Token Properties | D110: Source of Yield | E110: Interest income | F110: Official docs state interest income comes from short-duration U.S. Government Securities. | G110: 46139 | H110: Official | I110: High | J110: Interest income from these securities is recognized each market day and is reflected in the Fund's NAV | K110: https://docs.superstate.com/superstate-funds/ustb/income-fees-and-yield
B111: Superstate USTB | C111: Token Properties | D111: Yield Distribution Method | E111: Accrual | F111: Yield is reflected in NAV/S rather than paid as a separate distribution in reviewed docs. | G111: 46139 | H111: Official | I111: High | J111: Interest income from these securities is recognized each market day and is reflected in the Fund's NAV
B112: Superstate USTB | C112: Token Properties | D112: Supply | E112: Uncapped | F112: Official smart-contract docs state there are no limits for subscriptions. | G112: 46139 | H112: Official | I112: Medium | J112: There are no limits for subscriptions. | K112: https://docs.superstate.com/welcome-to-superstate/smart-contracts
B113: Superstate USTB | C113: DLT | D113: DeFi Integrations | E113: Other (Aave borrowing and lending) | F113: Official product page identifies Aave as a DeFi integration with borrowing and lending usage. | G113: 46139 | H113: Official | I113: High | J113: Tokenized shares are supported in the following DeFi protocols | Aave | Borrowing and lending | K113: https://superstate.com/assets/ustb
B114: Superstate USTB | C114: DLT | D114: Smart Contract | E114: Minting/subscription; redemption/burn; transfer permissioning; bridging; oracle price reporting | F114: Official smart-contract docs describe minting, redemption/burn, allowlist permissioning, bridging, and oracle pricing. | G114: 46139 | H114: Official | I114: High | J114: Mint; Redeem; Transfers; Bridging; Superstate USTB Continuous Price Oracle | K114: https://docs.superstate.com/welcome-to-superstate/smart-contracts
B115: Superstate USTB | C115: Economy | D115: Protocol fees | E115: Custody Fee | F115: management fee; official docs explicitly list custodial fees among fund expenses reflected in NAV. | G115: 46139 | H115: Official | I115: Medium | J115: including custodial, administrative, and audit fees, and pays up to 15bps management fee | K115: https://docs.superstate.com/superstate-funds/ustb/income-fees-and-yield
B116: Superstate USTB | C116: Economy | D116: Primary Market Access | E116: Qualified investors only; KYC gated; Whitelisted only | F116: Superstate Funds are limited to Qualified Purchasers after eligibility review, accreditation/AML checks, investment agreement, and allowlist setup. | G116: 46139 | H116: Official | I116: High | J116: Only available to Qualified Purchasers; compliance checks, anti-money laundering (AML) screening, and accreditation status; Allowlist | K116: https://docs.superstate.com/welcome-to-superstate/onboarding
A117: 6 | B117: WisdomTree Treasury Money Market Digital Fund (WTGXX) | C117: Governance | D117: Incorporation Jurisdiction | E117: USA | F117: The Trust is a Delaware statutory trust registered under the U.S. 1940 Act. | G117: 46139 | H117: Regulatory filing | I117: High | J117: The Trust was established as a Delaware statutory trust | K117: https://www.sec.gov/Archives/edgar/data/1859001/000121465924016339/ck0001859001-20240630a1v3.htm
B118: WisdomTree Treasury Money Market Digital Fund (WTGXX) | C118: Governance | D118: Legal Entity (Wrapper) | E118: Bankruptcy remote vehicle: Trust | F118: WTGXX is a series of WisdomTree Digital Trust, a Delaware statutory trust. | G118: 46139 | H118: Regulatory filing | I118: High | J118: The Trust was established as a Delaware statutory trust
B119: WisdomTree Treasury Money Market Digital Fund (WTGXX) | C119: Governance | D119: Voting | E119: Yes (shareholder voting; one vote per share when required) | F119: SAI states each share has one vote on matters requiring shareholder vote. | G119: 46139 | H119: Regulatory filing | I119: High | J119: Each share has one vote with respect to matters upon which a shareholder vote is required | K119: https://www.sec.gov/Archives/edgar/data/1859001/000121465925012990/wtd4485apospea8.htm
B120: WisdomTree Treasury Money Market Digital Fund (WTGXX) | C120: Asset | D120: Custody Arrangement | E120: Institutional custodian (regulated) | F120: BNY Mellon is named administrator and custodian for the Funds. | G120: 46139 | H120: Regulatory filing | I120: High | J120: The Bank of New York Mellon serves as administrator and custodian for the Funds
B121: WisdomTree Treasury Money Market Digital Fund (WTGXX) | C121: Asset | D121: Ownership Structure | E121: SPV held | F121: Fund assets are held by the Trust/Fund structure; shares have pro-rata interests in Fund assets. | G121: 46139 | H121: Regulatory filing | I121: High | J121: Each share of a Fund has a pro rata interest in the assets of the Fund
B122: WisdomTree Treasury Money Market Digital Fund (WTGXX) | C122: Asset | D122: Dispute Forum | E122: AAA Arbitration; New York, New York | F122: WisdomTree Connect terms specify confidential binding arbitration in New York administered by AAA. | G122: 46139 | H122: Official | I122: Medium | J122: binding arbitration administered by the American Arbitration Association | K122: https://app.wisdomtreeconnect.com/web/order/terms-and-conditions
B123: WisdomTree Treasury Money Market Digital Fund (WTGXX) | C123: Asset | D123: Claim Type | E123: Pro-rata claim on asset (share of pooled underlying) | F123: SAI states each share has pro-rata interest in Fund assets. | G123: 46139 | H123: Regulatory filing | I123: High | J123: Each share of a Fund has a pro rata interest in the assets of the Fund | K123: https://www.sec.gov/Archives/edgar/data/1859001/000121465925012990/wtd4485apospea8.htm
B124: WisdomTree Treasury Money Market Digital Fund (WTGXX) | C124: Asset | D124: Entitlements | E124: Redemption right; Income distribution right; Governance/voting | F124: Docs disclose subscription/redemption, monthly distributions, and one vote per share when required. | G124: 46139 | H124: Official and regulatory filing | I124: High | J124: Income accrues daily and is paid monthly; Each share has one vote | K124: https://dataspanapi.wisdomtree.com/pdr/documents/WEBSITE_FUND_DETAILS/WDT/US/EN-US/WTGXX_3/
B125: WisdomTree Treasury Money Market Digital Fund (WTGXX) | C125: Asset | D125: Asset Type | E125: Fixed income (government/corporate bonds) | F125: Fact sheet top holdings are Treasury bills, Treasury FRN, and tri-party repo. | G125: 46139 | H125: Official | I125: High | J125: Top Holdings: TREASURY BILL; US TREASURY FRN; TRI-PARTY | K125: https://www.wisdomtree.com/-/media/us-media-files/documents/resource-library/fund-fact-sheets/digital/wtgxx.pdf
B126: WisdomTree Treasury Money Market Digital Fund (WTGXX) | C126: Asset | D126: Third-Party Audit | E126: Yes; annual; https://www.wisdomtreeconnect.com/prospectus-regulatory-reports | F126: FAQ says audited financials are available with fund reports. | G126: 46139 | H126: Official | I126: Medium | J126: Investors can find: Monthly portfolio holdings; Audited financials; Form N-CSR and N-CEN filings | K126: https://dataspanapi.wisdomtree.com/pdr/documents/WEBSITE_FUND_DETAILS/WDT/US/EN-US/WTGXX_3/
B127: WisdomTree Treasury Money Market Digital Fund (WTGXX) | C127: Asset | D127: On-Chain Proof | E127: UNKNOWN | F127: Official docs identify token contracts but no explicit on-chain proof-of-reserves mechanism was found. | G127: 46139 | H127: Official | I127: Low | J127: No explicit on-chain proof-of-reserves statement located in reviewed documentation. | K127: https://www.wisdomtree.com/-/media/us-media-files/documents/resource-library/fund-fact-sheets/digital/wtgxx.pdf
...

Sheet DefiLlama Top 100 RWA 
B2: As of February 2026, list by Market Capitalization
B3: Source link: | C3: https://defillama.com/rwa
B4: Rank | C4: Name | D4: Type | E4: RWA Classification | F4: Access Model | G4: Category | H4: Asset Class | I4: DeFi Active TVL | J4: Active Marketcap | K4: Onchain Marketcap | L4: Token Price | M4: Issuer | N4: Redeemable | O4: Attestations | P4: CEX Listed | Q4: KYC to Mint or Redeem | R4: KYC/Allowlisted/Whitelisted to Transfer/Hold | S4: Transferable | T4: Self Custody
B5: 1 | C5: Tether Gold (XAUT) | D5: Asset | E5: RWA | F5: Permissionless | G5: Tokenized Gold & Commodities | H5: Allocated gold token | I5: $178.54m | J5: $3.57b | K5: $3.57b | L5: 5009 | M5: TG Commodities Limited | N5: Yes | O5: Yes | P5: Yes | Q5: Yes | S5: Yes | T5: Yes
B6: 2 | C6: BlackRock BUIDL (BUIDL) | D6: Asset | E6: RWA | F6: Permissioned | G6: Tokenized Funds (T-Bills, Bonds, MMFs) | H6: Money market fund | I6: $22.8m | J6: $2.363b | K6: $2.363b | M6: BlackRock USD Institutional Digital Liquidity Fund Ltd. | N6: Yes | O6: Yes | Q6: Yes | R6: Yes | S6: Yes | T6: Yes
B7: 3 | C7: PAX Gold (PAXG) | D7: Asset | E7: RWA | F7: Permissionless | G7: Tokenized Gold & Commodities | H7: Allocated gold token | I7: $15.54m | J7: $2.218b | K7: $2.315b | L7: 5043 | M7: Paxos Trust Company, LLC | N7: Yes | O7: Yes | P7: Yes | Q7: Yes | S7: Yes | T7: Yes
B8: 4 | C8: US Yield Coin (USYC) | D8: Asset | E8: RWA | F8: Permissioned | G8: Tokenized Funds (T-Bills, Bonds, MMFs) | H8: Money market fund | I8: $37.13m | J8: $1.592b | K8: $1.592b | M8: Hashnote International Short Duration Yield Fund Ltd | N8: Yes | O8: Yes | P8: Yes | Q8: Yes | R8: Yes | S8: Yes | T8: Yes
B9: 5 | C9: Superstate USTB (USTB) | D9: Asset | E9: RWA | F9: Permissioned | G9: Tokenized Funds (T-Bills, Bonds, MMFs) | H9: Tokenized T-bills | I9: $79.64m | J9: $580.8m | K9: $755.21m | L9: 10.98 | M9: Superstate Trust | N9: Yes | O9: Yes | Q9: Yes | R9: Yes | S9: Yes | T9: Yes
B10: 6 | C10: WisdomTree Treasury Money Market Digital Fund (WTGXX) | D10: Asset | E10: RWA | F10: Permissioned | G10: Tokenized Funds (T-Bills, Bonds, MMFs) | H10: Money market fund | I10: $18.9m | J10: $583.57m | K10: $729.1m | L10: 1 | M10: WisdomTree Digital Trust | N10: Yes | O10: Yes | Q10: Yes | R10: Yes | S10: Yes | T10: Yes
B11: 7 | C11: Janus Henderson Anemoy AAA CLO Fund (JAAA) | D11: Asset | E11: RWA | F11: Permissioned | G11: RWA Lending / Private Credit | H11: Credit / corporate bond fund | I11: $2.55m | J11: $4.55m | K11: $721.93m | L11: 1.02 | M11: Anemoy Capital SPC Limited | N11: Yes | O11: Yes | Q11: Yes | R11: Yes | S11: Yes | T11: Yes
B12: 8 | C12: Janus Henderson Anemoy Treasury Fund (JTRSY) | D12: Asset | E12: RWA | F12: Permissioned | G12: Tokenized Funds (T-Bills, Bonds, MMFs) | H12: Tokenized T-bills | I12: 0 | J12: $1.46m | K12: $567.69m | L12: 1.09 | M12: Anemoy Capital SPC Limited | N12: Yes | O12: Yes | Q12: Yes | R12: Yes | S12: Yes | T12: Yes
B13: 9 | C13: Ondo OUSG (OUSG) | D13: Asset | E13: RWA | F13: Permissioned | G13: Tokenized Funds (T-Bills, Bonds, MMFs) | H13: Tokenized T-bills | I13: $38.55m | J13: $463.46m | K13: $551.07m | L13: 114.29 | M13: Ondo I LP | N13: Yes | O13: Yes | Q13: Yes | R13: Yes | S13: Yes | T13: Yes
B14: 10 | C14: BlackRock USD Institutional Digital Liquidity Fund - I Class (BUIDL-I) | D14: Asset | E14: RWA | F14: Permissioned | G14: Tokenized Funds (T-Bills, Bonds, MMFs) | H14: Money market fund | I14: 0 | J14: $279.78m | K14: $414.95m | L14: 1 | M14: BlackRock USD Institutional Digital Liquidity Fund Ltd. | N14: Yes | O14: Yes | Q14: Yes | R14: Yes | S14: Yes | T14: Yes
B15: 11 | C15: Hastra PRIME (PRIME) | D15: Asset | E15: RWA | F15: Permissionless | G15: RWA Yield / Wrapper | H15: Yield bearing RWA pool | I15: $283.66m | K15: $296.7m | L15: 1.01 | M15: Hastra | N15: Yes | O15: Yes | Q15: Yes | S15: Yes | T15: Yes
B16: 12 | C16: Franklin OnChain U.S. Government Money Fund (BENJI) | D16: Asset | E16: RWA | F16: Permissioned | G16: Tokenized Funds (T-Bills, Bonds, MMFs) | H16: Money market fund | I16: 0 | J16: $221.36m | K16: $221.36m | L16: 1 | M16: Franklin Templeton Trust | N16: Yes | O16: Yes | Q16: Yes | R16: Yes | S16: Yes | T16: Yes
B17: 13 | C17: Superstate Crypto Carry Fund (USCC) | D17: Asset | E17: RWA | F17: Permissioned | G17: Tokenized Funds (T-Bills, Bonds, MMFs) | H17: Mixed RWA fund | I17: $140.35m | J17: $178.39m | K17: $220.65m | L17: 11.47 | M17: Superstate Asset Trust | N17: Yes | O17: Yes | Q17: Yes | R17: Yes | S17: Yes | T17: Yes
B18: 14 | C18: Exodus Movement, Inc. Class B (EXODB) | D18: Asset | E18: RWA | F18: Permissioned | G18: Tokenized Stocks & Equities | H18: Single stock fully backed | I18: 0 | J18: 0 | K18: $214.92m | L18: 11.27 | M18: Exodus Movement, Inc. | O18: Yes | Q18: Yes | R18: Yes | S18: Yes | T18: Yes
B19: 15 | C19: Theo Network thBill (thBILL) | D19: Asset | E19: Programmable Finance | F19: Permissioned | G19: Tokenized Funds (T-Bills, Bonds, MMFs) | H19: Tokenized T-bills | I19: $51.98m | J19: $214.48m | K19: $214.48m | L19: 1.01 | M19: Theo Protocol Corporation | O19: No | P19: Yes | Q19: Yes | R19: Yes | S19: Yes | T19: Yes
B20: 16 | C20: Fidelity Digital Interest Token (FDIT) | D20: Asset | E20: RWA | F20: Permissioned | G20: Tokenized Funds (T-Bills, Bonds, MMFs) | H20: Money market fund | I20: 0 | J20: $179.36m | K20: $179.36m | L20: 1 | M20: Fidelity Hereford Street Trust | N20: Yes | O20: Yes | Q20: Yes | R20: Yes | S20: Yes | T20: Yes
B21: 17 | C21: EUTBL by Spiko (EUTBL) | D21: Asset | E21: RWA | F21: Permissioned | G21: Tokenized Funds (T-Bills, Bonds, MMFs) | H21: Money market fund | I21: $2.22m | K21: $172.69m | L21: 1.24 | M21: Spiko | N21: Yes | O21: Yes | Q21: Yes | R21: Yes | S21: Yes | T21: Yes
B22: 18 | C22: Spiko US T-Bills Money Market Fund (USTBL) | D22: Asset | E22: RWA | F22: Permissioned | G22: Tokenized Funds (T-Bills, Bonds, MMFs) | H22: Tokenized T-bills | I22: 0 | K22: $163.01m | L22: 1.07 | M22: Spiko (Spiko SICAV sub-fund) | N22: Yes | O22: Yes | Q22: Yes | R22: Yes | S22: Yes | T22: Yes
B23: 19 | C23: Mantle Index Four Fund (MI4) | D23: Asset | E23: RWA | F23: Permissioned | G23: Tokenized Crypto Funds | H23: Crypto index fund | I23: 0 | J23: $122.38m | K23: $122.38m | L23: 90.54 | M23: Mantle Index Four | N23: Yes | O23: No | Q23: Yes | R23: Yes | S23: Yes | T23: Yes
B24: 20 | C24: mF-ONE (MF-ONE) | D24: Asset | E24: RWA | F24: Permissionless | G24: RWA Lending / Private Credit | H24: Private credit pool | I24: $31.46m | J24: $35.99m | K24: $121m | L24: 1.05 | M24: Midas Software GmbH | N24: Yes | O24: Yes | Q24: Yes | S24: Yes | T24: Yes
B25: 21 | C25: Tesla xStock (TSLAx) | D25: Asset | E25: RWA | F25: Permissionless | G25: Tokenized Stocks & Equities | H25: Single stock fully backed | I25: $3.34m | J25: $52.53m | K25: $111.84m | L25: 417.08 | M25: Backed Assets (JE) Limited | N25: Yes | O25: Yes | P25: Yes | Q25: Yes | S25: Yes | T25: Yes
B26: 22 | C26: Apollo Diversified Credit Securitize Fund (ACRED) | D26: Asset | E26: RWA | F26: Permissioned | G26: RWA Lending / Private Credit | H26: Private credit pool | I26: $44.63m | J26: $107.18m | K26: $107.18m | L26: 1097 | M26: Securitize Tokenized Apollo Diversified Credit Fund | N26: Yes | O26: Yes | Q26: Yes | R26: Yes | S26: Yes | T26: Yes
B27: 23 | C27: Securitize AAA CLO Tokenized Fund (STAC) | D27: Asset | E27: RWA | F27: Permissioned | G27: Tokenized Funds (T-Bills, Bonds, MMFs) | H27: Credit / corporate bond fund | I27: 0 | J27: $105.86m | K27: $105.86m | L27: 1007 | M27: Securitize AAA CLO Tokenized Fund | N27: Yes | O27: No | Q27: Yes | R27: Yes | S27: Yes | T27: Yes
B28: 24 | C28: Pleasing Gold (PGOLD) | D28: Asset | E28: RWA | F28: Permissionless | G28: Tokenized Gold & Commodities | H28: Allocated gold token | I28: $2.92m | J28: $97.56m | K28: $97.56m | L28: 5002 | M28: Pleasing International Limited | N28: Yes | O28: Yes | Q28: Yes | S28: Yes | T28: Yes
B29: 25 | C29: Onchain Yield Coin (ONyc) | D29: Asset | E29: RWA | F29: Permissionless | G29: RWA Lending / Private Credit | H29: Reinsurance backed RWA pool | I29: $66.18m | J29: $95.77m | K29: $97.29m | L29: 1.07 | M29: On Re SAC Ltd | N29: Yes | O29: Yes | Q29: Yes | S29: Yes | T29: Yes
B30: 26 | C30: OpenEden T-Bills (TBILL) | D30: Asset | E30: RWA | F30: Permissioned | G30: Tokenized Funds (T-Bills, Bonds, MMFs) | H30: Tokenized T-bills | I30: 0 | J30: $94.23m | K30: $94.23m | M30: Treasury Bills Institutional Liquidity Limited | N30: Yes | O30: Yes | Q30: Yes | R30: Yes | S30: Yes | T30: Yes
B31: 27 | C31: NVIDIA xStock (NVDAx) | D31: Asset | E31: RWA | F31: Permissionless | G31: Tokenized Stocks & Equities | H31: Single stock fully backed | I31: $2.34m | J31: $19.43m | K31: $81.02m | L31: 182.96 | M31: Backed Assets (JE) Limited | N31: Yes | O31: Yes | P31: Yes | Q31: Yes | S31: Yes | T31: Yes
B32: 28 | C32: Circle xStock (CRCLx) | D32: Asset | E32: RWA | F32: Permissionless | G32: Tokenized Stocks & Equities | H32: Single stock fully backed | I32: $1.27m | J32: $23.67m | K32: $78.76m | L32: 60.43 | M32: Backed Assets (JE) Limited | N32: Yes | O32: Yes | P32: Yes | Q32: Yes | S32: Yes | T32: Yes
B33: 29 | C33: VanEck Treasury Fund (VBILL) | D33: Asset | E33: RWA | F33: Permissioned | G33: Tokenized Funds (T-Bills, Bonds, MMFs) | H33: Money market fund | I33: $14.12m | J33: $78.39m | K33: $78.39m | L33: 1 | M33: VanEck Treasury Fund, Ltd. | N33: Yes | O33: Yes | Q33: Yes | R33: Yes | S33: Yes | T33: Yes
B34: 30 | C34: SP500 xStock (SPYx) | D34: Asset | E34: RWA | F34: Permissionless | G34: Tokenized Stocks & Equities | H34: Equity index / basket token | I34: $2.8m | J34: $16.68m | K34: $78.25m | L34: 682.26 | M34: Backed Assets (JE) Limited | N34: Yes | O34: Yes | P34: Yes | Q34: Yes | S34: Yes | T34: Yes
B35: 31 | C35: Alphabet xStock (GOOGLx) | D35: Asset | E35: RWA | F35: Permissionless | G35: Tokenized Stocks & Equities | H35: Single stock fully backed | I35: 984020 | J35: $15.87m | K35: $77.22m | L35: 305.93 | M35: Backed Assets (JE) Limited | N35: Yes | O35: Yes | P35: Yes | Q35: Yes | S35: Yes | T35: Yes
B36: 32 | C36: Nasdaq xStock (QQQx) | D36: Asset | E36: RWA | F36: Permissionless | G36: Tokenized Stocks & Equities | H36: Equity index / basket token | I36: $2.99m | J36: $14.33m | K36: $76.25m | L36: 600.23 | M36: Backed Assets (JE) Limited | N36: Yes | O36: Yes | P36: Yes | Q36: Yes | S36: Yes | T36: Yes
B37: 33 | C37: ULTRA (ULTRA) | D37: Asset | E37: RWA | F37: Permissioned | G37: Tokenized Funds (T-Bills, Bonds, MMFs) | H37: Tokenized T-bills | I37: $66.83m | K37: $67.21m | L37: 1.03 | M37: Delta Master Trust | N37: Yes | O37: Yes | Q37: Yes | R37: Yes | S37: Yes | T37: Yes
B38: 34 | C38: Meta xStock (METAx) | D38: Asset | E38: RWA | F38: Permissionless | G38: Tokenized Stocks & Equities | H38: Single stock fully backed | I38: 62394 | J38: $3.34m | K38: $65.21m | L38: 639.64 | M38: Backed Assets (JE) Limited | N38: Yes | O38: Yes | P38: Yes | Q38: Yes | S38: Yes | T38: Yes
B39: 35 | C39: MicroStrategy xStock (MSTRx) | D39: Asset | E39: RWA | F39: Permissionless | G39: Tokenized Stocks & Equities | H39: Single stock fully backed | I39: 929677 | J39: $15.87m | K39: $65m | L39: 135.88 | M39: Backed Assets (JE) Limited | N39: Yes | O39: Yes | P39: Yes | Q39: Yes | S39: Yes | T39: Yes
B40: 36 | C40: Apple xStock (AAPLx) | D40: Asset | E40: RWA | F40: Permissionless | G40: Tokenized Stocks & Equities | H40: Single stock fully backed | I40: 109624 | J40: $5.21m | K40: $64.51m | L40: 255.95 | M40: Backed Assets (JE) Limited | N40: Yes | O40: Yes | P40: Yes | Q40: Yes | S40: Yes | T40: Yes
B41: 37 | C41: Resolv Liquidity Provider Token (RLP) | D41: Asset | E41: RWA | F41: Permissionless | G41: Tokenized Crypto Funds | H41: Crypto hedge fund | I41: $28.58m | K41: $63.51m | L41: 1.28 | M41: Resolv | N41: Yes | O41: Yes | Q41: Yes | S41: Yes | T41: Yes
B42: 38 | C42: Matrixdock XAUm (XAUM) | D42: Asset | E42: RWA | F42: Permissionless | G42: Tokenized Gold & Commodities | H42: Allocated gold token | I42: $2.88m | J42: $61.1m | K42: $61.1m | L42: 4977 | M42: Matrix Infinitus (Hong Kong) Limited | N42: Yes | O42: Yes | Q42: Yes | S42: Yes | T42: Yes
B43: 39 | C43: Alphabet Class A (Ondo Tokenized Stock) (GOOGLon) | D43: Asset | E43: RWA | F43: Permissionless | G43: Tokenized Stocks & Equities | H43: Single stock fully backed | I43: 44518 | J43: $59.71m | K43: $59.71m | L43: 305.87 | M43: Ondo Global Markets (BVI) Limited | N43: Yes | O43: Yes | P43: Yes | Q43: Yes | S43: Yes | T43: Yes
B44: 40 | C44: TQQQ xStock (TQQQx) | D44: Asset | E44: RWA | F44: Permissionless | G44: Tokenized Stocks & Equities | H44: Equity index / basket token | I44: 0 | J44: $1.47m | K44: $57.37m | L44: 97.59 | M44: Backed Assets (JE) Limited | N44: Yes | O44: Yes | P44: Yes | Q44: Yes | S44: Yes | T44: Yes
B45: 41 | C45: Coinbase xStock (COINx) | D45: Asset | E45: RWA | F45: Permissionless | G45: Tokenized Stocks & Equities | H45: Single stock fully backed | I45: 71615 | J45: $4.87m | K45: $54.15m | L45: 167.12 | M45: Backed Assets (JE) Limited | N45: Yes | O45: Yes | P45: Yes | Q45: Yes | S45: Yes | T45: Yes
B46: 42 | C46: Tether Gold Tokens (XAUT0) | D46: Asset | E46: RWA | F46: Permissionless | G46: Tokenized Gold & Commodities | H46: Allocated gold token | I46: $21.27m | K46: $52.38m | L46: 4990 | M46: USDT0 Network | N46: Yes | O46: Yes | Q46: Yes | S46: Yes | T46: Yes
B47: 43 | C47: Eli Lilly xStock (LLYx) | D47: Asset | E47: RWA | F47: Permissionless | G47: Tokenized Stocks & Equities | H47: Single stock fully backed | I47: 0 | J47: 430195 | K47: $51.36m | L47: 1041 | M47: Backed Assets (JE) Limited | N47: Yes | O47: Yes | P47: Yes | Q47: Yes | S47: Yes | T47: Yes
B48: 44 | C48: Amazon xStock (AMZNx) | D48: Asset | E48: RWA | F48: Permissionless | G48: Tokenized Stocks & Equities | H48: Single stock fully backed | I48: 196923 | J48: $4.14m | K48: $50.04m | L48: 199.48 | M48: Backed Assets (JE) Limited | N48: Yes | O48: Yes | P48: Yes | Q48: Yes | S48: Yes | T48: Yes
B49: 45 | C49: Robinhood xStock (HOODx) | D49: Asset | E49: RWA | F49: Permissionless | G49: Tokenized Stocks & Equities | H49: Single stock fully backed | I49: 117706 | J49: $3.03m | K49: $47.25m | L49: 76.3 | M49: Backed Assets (JE) Limited | N49: Yes | O49: Yes | P49: Yes | Q49: Yes | S49: Yes | T49: Yes
B50: 46 | C50: Gold xStock (GLDx) | D50: Asset | E50: RWA | F50: Permissionless | G50: Tokenized Stocks & Equities | H50: Equity index / basket token | I50: 172051 | J50: $8.72m | K50: $43.61m | L50: 461.16 | M50: Backed Assets (JE) Limited | N50: Yes | O50: Yes | P50: Yes | Q50: Yes | S50: Yes | T50: Yes
B51: 47 | C51: Berkshire Hathaway xStock (BRK.Bx) | D51: Asset | E51: RWA | F51: Permissionless | G51: Tokenized Stocks & Equities | H51: Single stock fully backed | I51: 25 | J51: 836921 | K51: $41.58m | L51: 512.85 | M51: Backed Assets (JE) Limited | N51: Yes | O51: Yes | P51: Yes | Q51: Yes | S51: Yes | T51: Yes
B52: 48 | C52: Home Depot xStock (HDx) | D52: Asset | E52: RWA | F52: Permissionless | G52: Tokenized Stocks & Equities | H52: Single stock fully backed | I52: 0 | J52: 158766 | K52: $40.99m | L52: 391.6 | M52: Backed Assets (JE) Limited | N52: Yes | O52: Yes | P52: Yes | Q52: Yes | S52: Yes | T52: Yes
B53: 49 | C53: Circle Internet Group (Ondo Tokenized Stock) (CRCLon) | D53: Asset | E53: RWA | F53: Permissionless | G53: Tokenized Stocks & Equities | H53: Single stock fully backed | I53: 21440 | J53: $40.06m | K53: $40.06m | L53: 60.24 | M53: Ondo Global Markets (BVI) Limited | N53: Yes | O53: Yes | P53: Yes | Q53: Yes | S53: Yes | T53: Yes
B54: 50 | C54: Honeywell xStock (HONx) | D54: Asset | E54: RWA | F54: Permissionless | G54: Tokenized Stocks & Equities | H54: Single stock fully backed | I54: 0 | J54: 313971 | K54: $38.64m | L54: 247.34 | M54: Backed Assets (JE) Limited | N54: Yes | O54: Yes | P54: Yes | Q54: Yes | S54: Yes | T54: Yes
B55: 51 | C55: Exxon Mobil xStock (XOMx) | D55: Asset | E55: RWA | F55: Permissionless | G55: Tokenized Stocks & Equities | H55: Single stock fully backed | I55: 0 | J55: 625062 | K55: $38.39m | L55: 148.78 | M55: Backed Assets (JE) Limited | N55: Yes | O55: Yes | P55: Yes | Q55: Yes | S55: Yes | T55: Yes
B56: 52 | C56: Mastercard xStock (MAx) | D56: Asset | E56: RWA | F56: Permissionless | G56: Tokenized Stocks & Equities | H56: Single stock fully backed | I56: 0 | J56: 206990 | K56: $38.14m | L56: 519.23 | M56: Backed Assets (JE) Limited | N56: Yes | O56: Yes | P56: Yes | Q56: Yes | S56: Yes | T56: Yes
B57: 53 | C57: mTBILL (mTBILL) | D57: Asset | E57: RWA | F57: Permissionless | G57: Tokenized Funds (T-Bills, Bonds, MMFs) | H57: Tokenized T-bills | I57: 4389 | J57: 448688 | K57: $37.24m | L57: 1.05 | M57: Midas Software GmbH | N57: Yes | O57: Yes | Q57: Yes | S57: Yes | T57: Yes
B58: 54 | C58: PepsiCo xStock (PEPx) | D58: Asset | E58: RWA | F58: Permissionless | G58: Tokenized Stocks & Equities | H58: Single stock fully backed | I58: 0 | J58: 346067 | K58: $37.07m | L58: 168.12 | M58: Backed Assets (JE) Limited | N58: Yes | O58: Yes | P58: Yes | Q58: Yes | S58: Yes | T58: Yes
B59: 55 | C59: Intel xStock (INTCx) | D59: Asset | E59: RWA | F59: Permissionless | G59: Tokenized Stocks & Equities | H59: Single stock fully backed | I59: 100 | J59: $1.24m | K59: $36.87m | L59: 46.63 | M59: Backed Assets (JE) Limited | N59: Yes | O59: Yes | P59: Yes | Q59: Yes | S59: Yes | T59: Yes
B60: 56 | C60: Microsoft xStock (MSFTx) | D60: Asset | E60: RWA | F60: Permissionless | G60: Tokenized Stocks & Equities | H60: Single stock fully backed | I60: 0 | J60: $1.78m | K60: $36.71m | L60: 407.02 | M60: Backed Assets (JE) Limited | N60: Yes | O60: Yes | P60: Yes | Q60: Yes | S60: Yes | T60: Yes
B61: 57 | C61: Procter & Gamble xStock (PGx) | D61: Asset | E61: RWA | F61: Permissionless | G61: Tokenized Stocks & Equities | H61: Single stock fully backed | I61: 16 | J61: 470402 | K61: $36.41m | L61: 162.21 | M61: Backed Assets (JE) Limited | N61: Yes | O61: Yes | P61: Yes | Q61: Yes | S61: Yes | T61: Yes
B62: 58 | C62: AbbVie xStock (ABBVx) | D62: Asset | E62: RWA | F62: Permissionless | G62: Tokenized Stocks & Equities | H62: Single stock fully backed | I62: 0 | J62: 309275 | K62: $36.03m | L62: 233.59 | M62: Backed Assets (JE) Limited | N62: Yes | O62: Yes | P62: Yes | Q62: Yes | S62: Yes | T62: Yes
B63: 59 | C63: McDonald's xStock (MCDx) | D63: Asset | E63: RWA | F63: Permissionless | G63: Tokenized Stocks & Equities | H63: Single stock fully backed | I63: 19636 | J63: 832148 | K63: $35.88m | L63: 329.25 | M63: Backed Assets (JE) Limited | N63: Yes | O63: Yes | P63: Yes | Q63: Yes | S63: Yes | T63: Yes
B64: 60 | C64: Broadcom xStock (AVGOx) | D64: Asset | E64: RWA | F64: Permissionless | G64: Tokenized Stocks & Equities | H64: Single stock fully backed | I64: 0 | J64: 723503 | K64: $35.78m | L64: 325.93 | M64: Backed Assets (JE) Limited | N64: Yes | O64: Yes | P64: Yes | Q64: Yes | S64: Yes | T64: Yes
B65: 61 | C65: Vanguard xStock (VTIx) | D65: Asset | E65: RWA | F65: Permissionless | G65: Tokenized Stocks & Equities | H65: Equity index / basket token | I65: 0 | J65: $1.11m | K65: $35.15m | L65: 337.96 | M65: Backed Assets (JE) Limited | N65: Yes | O65: Yes | P65: Yes | Q65: Yes | S65: Yes | T65: Yes
B66: 62 | C66: iShares Silver Trust (Ondo Tokenized Stock) (SLVon) | D66: Asset | E66: RWA | F66: Permissionless | G66: Tokenized Stocks & Equities | H66: Equity index / basket token | I66: 143462 | J66: $35.14m | K66: $35.14m | L66: 70.03 | M66: Ondo Global Markets (BVI) Limited | N66: Yes | O66: Yes | P66: Yes | Q66: Yes | S66: Yes | T66: Yes
B67: 63 | C67: Coca-Cola xStock (KOx) | D67: Asset | E67: RWA | F67: Permissionless | G67: Tokenized Stocks & Equities | H67: Single stock fully backed | I67: 257 | J67: 433291 | K67: $34.83m | L67: 79.08 | M67: Backed Assets (JE) Limited | N67: Yes | O67: Yes | P67: Yes | Q67: Yes | S67: Yes | T67: Yes
B68: 64 | C68: Comcast xStock (CMCSAx) | D68: Asset | E68: RWA | F68: Permissionless | G68: Tokenized Stocks & Equities | H68: Single stock fully backed | I68: 101 | J68: 336458 | K68: $34.77m | L68: 33.64 | M68: Backed Assets (JE) Limited | N68: Yes | O68: Yes | P68: Yes | Q68: Yes | S68: Yes | T68: Yes
B69: 65 | C69: T Rize (TRIZE) | D69: Platform | E69: Non-RWA (Platform) | F69: Permissionless | G69: Tokenized Real Estate | H69: RWA lending market | I69: 28561 | J69: $34.71m | K69: $34.71m | L69: 0.007 | M69: T Rize Group | O69: No | S69: Yes | T69: Yes
B70: 66 | C70: Reental (REENTAL) | D70: Platform | E70: Non-RWA (Platform) | F70: Permissioned | G70: Tokenized Real Estate | H70: RWA lending market | I70: 0 | K70: $33.46m | L70: 0.16 | M70: Reental | O70: No | Q70: Yes | R70: Yes | S70: Yes | T70: Yes
B71: 67 | C71: CrowdStrike xStock (CRWDx) | D71: Asset | E71: RWA | F71: Permissionless | G71: Tokenized Stocks & Equities | H71: Single stock fully backed | I71: 0 | J71: 251763 | K71: $33.36m | L71: 428.21 | M71: Backed Assets (JE) Limited | N71: Yes | O71: Yes | P71: Yes | Q71: Yes | S71: Yes | T71: Yes
B72: 68 | C72: Cisco xStock (CSCOx) | D72: Asset | E72: RWA | F72: Permissionless | G72: Tokenized Stocks & Equities | H72: Single stock fully backed | I72: 0 | J72: 250962 | K72: $33.04m | L72: 77.9 | M72: Backed Assets (JE) Limited | N72: Yes | O72: Yes | P72: Yes | Q72: Yes | S72: Yes | T72: Yes
B73: 69 | C73: Thermo Fisher xStock (TMOx) | D73: Asset | E73: RWA | F73: Permissionless | G73: Tokenized Stocks & Equities | H73: Single stock fully backed | I73: 51 | J73: $23.5m | K73: $32.64m | L73: 509.2 | M73: Backed Assets (JE) Limited | N73: Yes | O73: Yes | P73: Yes | Q73: Yes | S73: Yes | T73: Yes
B74: 70 | C74: Danaher xStock (DHRx) | D74: Asset | E74: RWA | F74: Permissionless | G74: Tokenized Stocks & Equities | H74: Single stock fully backed | I74: 0 | J74: 226452 | K74: $31.12m | L74: 215.63 | M74: Backed Assets (JE) Limited | N74: Yes | O74: Yes | P74: Yes | Q74: Yes | S74: Yes | T74: Yes
B75: 71 | C75: Oracle xStock (ORCLx) | D75: Asset | E75: RWA | F75: Permissionless | G75: Tokenized Stocks & Equities | H75: Single stock fully backed | I75: 403 | J75: $1.02m | K75: $30.88m | L75: 162.86 | M75: Backed Assets (JE) Limited | N75: Yes | O75: Yes | P75: Yes | Q75: Yes | S75: Yes | T75: Yes
B76: 72 | C76: International Business Machines xStock (IBMx) | D76: Asset | E76: RWA | F76: Permissionless | G76: Tokenized Stocks & Equities | H76: Single stock fully backed | I76: 0 | J76: 264114 | K76: $29.96m | L76: 270.9 | M76: Backed Assets (JE) Limited | N76: Yes | O76: Yes | Q76: Yes | S76: Yes | T76: Yes
B77: 73 | C77: Micron Technology (Ondo Tokenized Stock) (MUon) | D77: Asset | E77: RWA | F77: Permissionless | G77: Tokenized Stocks & Equities | H77: Single stock fully backed | I77: 5005 | J77: $27.94m | K77: $29.68m | L77: 409.62 | M77: Ondo Global Markets (BVI) Limited | N77: Yes | O77: Yes | P77: Yes | Q77: Yes | S77: Yes | T77: Yes
B78: 74 | C78: Abbott xStock (ABTx) | D78: Asset | E78: RWA | F78: Permissionless | G78: Tokenized Stocks & Equities | H78: Single stock fully backed | I78: 0 | J78: 207002 | K78: $29.59m | L78: 112.15 | M78: Backed Assets (JE) Limited | N78: Yes | O78: Yes | P78: Yes | Q78: Yes | S78: Yes | T78: Yes
B79: 75 | C79: Accenture xStock (ACNx) | D79: Asset | E79: RWA | F79: Permissionless | G79: Tokenized Stocks & Equities | H79: Single stock fully backed | I79: 75 | J79: 192528 | K79: $29.45m | L79: 232.8 | M79: Backed Assets (JE) Limited | N79: Yes | O79: Yes | P79: Yes | Q79: Yes | S79: Yes | T79: Yes
B80: 76 | C80: SPDR S&P 500 ETF (Ondo Tokenized Stock) (SPYon) | D80: Asset | E80: RWA | F80: Permissionless | G80: Tokenized Stocks & Equities | H80: Equity index / basket token | I80: 286837 | J80: $27.39m | K80: $27.39m | L80: 683.69 | M80: Ondo Global Markets (BVI) Limited | N80: Yes | O80: Yes | P80: Yes | Q80: Yes | S80: Yes | T80: Yes
B81: 77 | C81: DFDV xStock (DFDVx) | D81: Asset | E81: RWA | F81: Permissionless | G81: Tokenized Stocks & Equities | H81: Single stock fully backed | I81: 8255 | J81: 700167 | K81: $26.51m | L81: 4.1 | M81: Backed Assets (JE) Limited | N81: Yes | O81: Yes | P81: Yes | Q81: Yes | S81: Yes | T81: Yes
B82: 78 | C82: AstraZeneca xStock (AZNx) | D82: Asset | E82: RWA | F82: Permissionless | G82: Tokenized Stocks & Equities | H82: Single stock fully backed | I82: 40 | J82: 192250 | K82: $23m | L82: 102.97 | M82: Backed Assets (JE) Limited | N82: Yes | O82: Yes | P82: Yes | Q82: Yes | S82: Yes | T82: Yes
B83: 79 | C83: Invesco QQQ (Ondo Tokenized Stock) (QQQon) | D83: Asset | E83: RWA | F83: Permissionless | G83: Tokenized Stocks & Equities | H83: Equity index / basket token | I83: 25799 | J83: $21.81m | K83: $22.7m | L83: 601.7 | M83: Ondo Global Markets (BVI) Limited | N83: Yes | O83: Yes | P83: Yes | Q83: Yes | S83: Yes | T83: Yes
B84: 80 | C84: iShares Core S&P 500 ETF (Ondo Tokenized Stock) (IVVon) | D84: Asset | E84: RWA | F84: Permissionless | G84: Tokenized Stocks & Equities | H84: Equity index / basket token | I84: 1598 | J84: $15.66m | K84: $21.7m | L84: 686.76 | M84: Ondo Global Markets (BVI) Limited | N84: Yes | O84: Yes | Q84: Yes | S84: Yes | T84: Yes
B85: 81 | C85: iShares 20+ Year Treasury Bond ETF (Ondo Tokenized Stock) (TLTon) | D85: Asset | E85: RWA | F85: Permissionless | G85: Tokenized Stocks & Equities | H85: Equity index / basket token | I85: 2271 | J85: $17.07m | K85: $19.17m | L85: 91.76 | M85: Ondo Global Markets (BVI) Limited | N85: Yes | O85: Yes | P85: Yes | Q85: Yes | S85: Yes | T85: Yes
B86: 82 | C86: ComTech Gold (CGO) | D86: Asset | E86: RWA | F86: Permissionless | G86: Tokenized Gold & Commodities | H86: Allocated gold token | I86: 80451 | K86: $17.3m | L86: 160.19 | M86: ComTech FZCO | N86: Yes | O86: Yes | Q86: Yes | S86: Yes | T86: Yes
B87: 83 | C87: iShares Core MSCI EAFE ETF (Ondo Tokenized Stock) (IEFAon) | D87: Asset | E87: RWA | F87: Permissionless | G87: Tokenized Stocks & Equities | H87: Equity index / basket token | I87: 1785 | J87: $10.58m | K87: $16.85m | L87: 99.64 | M87: Ondo Global Markets (BVI) Limited | N87: Yes | O87: Yes | P87: Yes | Q87: Yes | S87: Yes | T87: Yes
B88: 84 | C88: Backed CSPX Core S&P 500 (bCSPX) | D88: Asset | E88: RWA | F88: Permissionless | G88: Tokenized Stocks & Equities | H88: Equity index / basket token | I88: 19271 | J88: $7.9m | K88: $15.26m | L88: 735.38 | M88: Backed Assets (JE) Limited | N88: Yes | O88: Yes | P88: Yes | Q88: Yes | S88: Yes | T88: Yes
B89: 85 | C89: iShares Core US Aggregate Bond ETF (Ondo Tokenized Stock) (AGGon) | D89: Asset | E89: RWA | F89: Permissionless | G89: Tokenized Stocks & Equities | H89: Equity index / basket token | I89: 1287 | J89: $9.78m | K89: $14.57m | L89: 103.03 | M89: Ondo Global Markets (BVI) Limited | N89: Yes | O89: Yes | Q89: Yes | S89: Yes | T89: Yes
B90: 86 | C90: NVIDIA (Ondo Tokenized Stock) (NVDAon) | D90: Asset | E90: RWA | F90: Permissionless | G90: Tokenized Stocks & Equities | H90: Single stock fully backed | I90: 45104 | J90: $14.1m | K90: $14.1m | L90: 182.87 | M90: Ondo Global Markets (BVI) Limited | N90: Yes | O90: Yes | P90: Yes | Q90: Yes | S90: Yes | T90: Yes
B91: 87 | C91: Backed IB01 $ Treasury Bond (bIB01) | D91: Asset | E91: RWA | F91: Permissionless | G91: Tokenized Funds (T-Bills, Bonds, MMFs) | H91: Tokenized T-bills | I91: 3670 | J91: $3.66m | K91: $13.77m | L91: 119.36 | M91: Backed Assets (JE) Limited | N91: Yes | O91: Yes | P91: Yes | Q91: Yes | S91: Yes | T91: Yes
B92: 88 | C92: iShares Gold Trust (Ondo Tokenized Stock) (IAUon) | D92: Asset | E92: RWA | F92: Permissionless | G92: Tokenized Stocks & Equities | H92: Equity index / basket token | I92: 5947 | J92: $13.48m | K92: $13.48m | L92: 94.98 | M92: Ondo Global Markets (BVI) Limited | N92: Yes | O92: Yes | Q92: Yes | S92: Yes | T92: Yes
B93: 89 | C93: Tesla (Ondo Tokenized Stock) (TSLAon) | D93: Asset | E93: RWA | F93: Permissionless | G93: Tokenized Stocks & Equities | H93: Single stock fully backed | I93: 89521 | J93: $13.07m | K93: $13.07m | L93: 417.4 | M93: Ondo Global Markets (BVI) Limited | N93: Yes | O93: Yes | P93: Yes | Q93: Yes | S93: Yes | T93: Yes
B94: 90 | C94: Walmart xStock (WMTx) | D94: Asset | E94: RWA | F94: Permissionless | G94: Tokenized Stocks & Equities | H94: Single stock fully backed | I94: 46 | J94: 213998 | K94: $12.91m | L94: 141.37 | M94: Backed Assets (JE) Limited | N94: Yes | O94: Yes | P94: Yes | Q94: Yes | S94: Yes | T94: Yes
B95: 91 | C95: Spiko Cash and Carry Dollar (SPKCC) | D95: Asset | E95: Programmable Finance | F95: Permissioned | G95: Tokenized Crypto Funds | H95: Institutional fund | I95: $12.29m | K95: $12.29m | L95: 1 | M95: Spiko | N95: Yes | O95: Yes | Q95: Yes | R95: Yes | S95: Yes | T95: Yes
B96: 92 | C96: iShares TIPS Bond ETF (Ondo Tokenized Stock) (TIPon) | D96: Asset | E96: RWA | F96: Permissionless | G96: Tokenized Stocks & Equities | H96: Equity index / basket token | I96: 918 | J96: $11.27m | K96: $11.27m | L96: 112.57 | M96: Ondo Global Markets (BVI) Limited | N96: Yes | O96: Yes | P96: Yes | Q96: Yes | S96: Yes | T96: Yes
B97: 93 | C97: Backed ERNX € Ultrashort Bond (bERNX) | D97: Asset | E97: RWA | F97: Permissionless | G97: Tokenized Funds (T-Bills, Bonds, MMFs) | H97: Credit / corporate bond fund | I97: 0 | J97: 0 | K97: $11.09m | L97: 5.54 | M97: Backed Assets (JE) Limited | N97: Yes | O97: Yes | P97: Yes | Q97: Yes | S97: Yes | T97: Yes
B98: 94 | C98: iShares MSCI EAFE ETF (Ondo Tokenized Stock) (EFAon) | D98: Asset | E98: RWA | F98: Permissionless | G98: Tokenized Stocks & Equities | H98: Equity index / basket token | I98: 1257 | J98: $3.76m | K98: $10.96m | L98: 105.07 | M98: Ondo Global Markets (BVI) Limited | N98: Yes | O98: Yes | P98: Yes | Q98: Yes | S98: Yes | T98: Yes
B99: 95 | C99: iShares Core S&P Total US Stock Market ETF (Ondo Tokenized Stock) (ITOTon) | D99: Asset | E99: RWA | F99: Permissionless | G99: Tokenized Stocks & Equities | H99: Equity index / basket token | I99: 1054 | J99: $8.27m | K99: $10.33m | L99: 149.87 | M99: Ondo Global Markets (BVI) Limited | N99: Yes | O99: Yes | P99: Yes | Q99: Yes | S99: Yes | T99: Yes
B100: 96 | C100: Backed GOVIES 0-6 Months Euro Investment Grade (bC3M) | D100: Asset | E100: RWA | F100: Permissionless | G100: Tokenized Funds (T-Bills, Bonds, MMFs) | H100: Credit / corporate bond fund | I100: 0 | J100: 105 | K100: $10.22m | L100: 148.36 | M100: Backed Assets (JE) Limited | N100: Yes | O100: Yes | P100: Yes | Q100: Yes | S100: Yes | T100: Yes
B101: 97 | C101: Visa xStock (Vx) | D101: Asset | E101: RWA | F101: Permissionless | G101: Tokenized Stocks & Equities | H101: Single stock fully backed | I101: 0 | J101: 281811 | K101: $9.52m | L101: 329.47 | M101: Backed Assets (JE) Limited | N101: Yes | O101: Yes | P101: Yes | Q101: Yes | S101: Yes | T101: Yes
...
